Workbook

Sheet field_dictionary
A1: id | B1: table_name | C1: field_name | D1: label | E1: BVD Codes (via vlookup) | F1: is code for [Business Term] > Name | G1: Definition (from Collibra) | H1: internal_description | I1: external_description | J1: data_type | K1: data_precision | L1: data_scale | M1: api_lineage | N1: is_primary_key | O1: foreign_keys | P1: created_at | Q1: last_updated | R1: is_deprecated | S1: business_owner | T1: security_classification | U1: update_frequency | V1: display_pattern | W1: allowed_values | X1: validation_rules | Y1: dq_metrics | Z1: path_depth | AA1: domain | AB1: reference_table
A2: 154 | B2: acnc | C2: bvd_id_number | D2: BvD_ID_number | E2: =VLOOKUP(B2&" - "&D2,OrbisGeneric_mapping!C:F,3,0) -> BVD_ID_NUMBER | F2: =VLOOKUP(E2,Collibra!D:F,3,0) -> BvD ID number | G2: =VLOOKUP(E2,Collibra!D:F,2,0) -> <p class="MsoNormal"><span style="font-size: 9.0pt;font-family: Arial , sans-serif;color: rgb(11,33,44);">The BvD ID number is a company identifier that uniquely identifies each company included in at least one Bureau van Dijk product. The first two characters correspond to the ISO country code (according the ISO 3166-1 alpha-2 standard) where the company is incorporated. The rest of a BvD ID number may vary and be based on a national ID, an information provider's ID, an own internal ID.</span> As a result, BvD ID numbers may be subject to change due to changes in national IDs or an information provider's ID.</p> | J2: STRING | N2: FALSE | P2: 2025-08-29T13:46:54.659Z | Q2: 2025-08-29T13:46:54.663Z | R2: FALSE | Z2: 1
A3: 250 | B3: acnc | C3: charity_beneficiaries | D3: Charity_beneficiaries | E3: =VLOOKUP(B3&" - "&D3,OrbisGeneric_mapping!C:F,3,0) -> CHARITY_BENEFICIARIES | F3: =VLOOKUP(E3,Collibra!D:F,3,0) -> Charity Beneficiaries | G3: =VLOOKUP(E3,Collibra!D:F,2,0) -> <p>Charities are able to nominate one or more beneficiaries from the list. If a charity has reported that they assist a beneficiary group, a ‘Y’ will be recorded in the column for the relevant beneficiary. Otherwise, the field will be blank.</p> <p>Possible beneficiaries are as follows: Aboriginal_or_TSI; Adults; Aged_Persons; Children; Communities_Overseas; Early_Childhood; Ethnic_Groups; Families; Females; Financially_Disadvantaged; Gay_Lesbian_Bisexual; General_Community_in_Australia; Males; Migrants_Refugees_or_Asylum_Seekers; Other_Beneficiaries; Other_Charities; People_at_risk_of_homelessness; People_with_Chronic_Illness; People_with_Disabilities; Pre_Post_Release_Offenders; Rural_Regional_Remote_Communities; Unemployed_Person; Veterans_or_their_families; Victims_of_crime; Victims_of_Disasters Youth</p> | J3: STRING | N3: FALSE | P3: 2025-08-29T13:46:54.659Z | Q3: 2025-08-29T13:46:54.663Z | R3: FALSE | Z3: 1
A4: 226 | B4: acnc | C4: charity_type | D4: Charity_type | E4: =VLOOKUP(B4&" - "&D4,OrbisGeneric_mapping!C:F,3,0) -> CHARITY_TYPE | F4: =VLOOKUP(E4,Collibra!D:F,3,0) -> Charity Type | G4: =VLOOKUP(E4,Collibra!D:F,2,0) -> Charities can be registered with one or more charity ‘subtypes’. These subtypes are categories that reflect the charity’s charitable purpose, for example ‘advancing education’ or ‘advancing health’. A charity’s purpose is the reason it has been set up, or what its activities work. | J4: STRING | N4: FALSE | P4: 2025-08-29T13:46:54.659Z | Q4: 2025-08-29T13:46:54.663Z | R4: FALSE | Z4: 1
A5: 234 | B5: acnc | C5: countries_of_operations | D5: Countries_of_operations | E5: =VLOOKUP(B5&" - "&D5,OrbisGeneric_mapping!C:F,3,0) -> CHARITY_OPERATING_COUNTRIES | F5: =VLOOKUP(E5,Collibra!D:F,3,0) -> Countries of operations | G5: =VLOOKUP(E5,Collibra!D:F,2,0) -> If the charity operates overseas, this column will contain data. The information in this field is based on the ISO 3166-1 alpha 3 codes. Where a charity operates in more than one overseas location, there will be multiple country codes. | J5: STRING | N5: FALSE | P5: 2025-08-29T13:46:54.659Z | Q5: 2025-08-29T13:46:54.663Z | R5: FALSE | Z5: 1
A6: 258 | B6: acnc | C6: date_established | D6: Date_established | E6: =VLOOKUP(B6&" - "&D6,OrbisGeneric_mapping!C:F,3,0) -> CHARITY_DATE_ORGANISATION_ESTABLISHED | F6: =VLOOKUP(E6,Collibra!D:F,3,0) -> Date Organisation Established | G6: =VLOOKUP(E6,Collibra!D:F,2,0) -> This field contains the date that the charity was established. Some organisations run as not-for-profits for years before deciding to register as charities. | J6: STRING | N6: FALSE | P6: 2025-08-29T13:46:54.659Z | Q6: 2025-08-29T13:46:54.663Z | R6: FALSE | Z6: 1
A7: 282 | B7: acnc | C7: date_established_day | D7: Date_established_day | E7: =VLOOKUP(B7&" - "&D7,OrbisGeneric_mapping!C:F,3,0) -> #N/A | F7: =VLOOKUP(E7,Collibra!D:F,3,0) -> #N/A | G7: =VLOOKUP(E7,Collibra!D:F,2,0) -> #N/A | J7: STRING | N7: FALSE | P7: 2025-08-29T13:46:54.659Z | Q7: 2025-08-29T13:46:54.663Z | R7: FALSE | Z7: 1
A8: 274 | B8: acnc | C8: date_established_month | D8: Date_established_month | E8: =VLOOKUP(B8&" - "&D8,OrbisGeneric_mapping!C:F,3,0) -> #N/A | F8: =VLOOKUP(E8,Collibra!D:F,3,0) -> #N/A | G8: =VLOOKUP(E8,Collibra!D:F,2,0) -> #N/A | J8: STRING | N8: FALSE | P8: 2025-08-29T13:46:54.659Z | Q8: 2025-08-29T13:46:54.663Z | R8: FALSE | Z8: 1
A9: 266 | B9: acnc | C9: date_established_year | D9: Date_established_year | E9: =VLOOKUP(B9&" - "&D9,OrbisGeneric_mapping!C:F,3,0) -> #N/A | F9: =VLOOKUP(E9,Collibra!D:F,3,0) -> #N/A | G9: =VLOOKUP(E9,Collibra!D:F,2,0) -> #N/A | J9: STRING | N9: FALSE | P9: 2025-08-29T13:46:54.659Z | Q9: 2025-08-29T13:46:54.663Z | R9: FALSE | Z9: 1
A10: 290 | B10: acnc | C10: last_delivery_date | D10: Last_delivery_date | E10: =VLOOKUP(B10&" - "&D10,OrbisGeneric_mapping!C:F,3,0) -> CHARITY_LAST_DELIVERY_DATE | F10: =VLOOKUP(E10,Collibra!D:F,3,0) -> Last delivery date | G10: =VLOOKUP(E10,Collibra!D:F,2,0) -> This field is populated with the most recent date on which we received Australian Charities and Not-for-profits Commission data, based on a record we keep of historical data received (DD/MM/YYYY). | J10: STRING | N10: FALSE | P10: 2025-08-29T13:46:54.659Z | Q10: 2025-08-29T13:46:54.663Z | R10: FALSE | Z10: 1
A11: 314 | B11: acnc | C11: last_delivery_date_day | D11: Last_delivery_date_day | E11: =VLOOKUP(B11&" - "&D11,OrbisGeneric_mapping!C:F,3,0) -> #N/A | F11: =VLOOKUP(E11,Collibra!D:F,3,0) -> #N/A | G11: =VLOOKUP(E11,Collibra!D:F,2,0) -> #N/A | J11: STRING | N11: FALSE | P11: 2025-08-29T13:46:54.659Z | Q11: 2025-08-29T13:46:54.663Z | R11: FALSE | Z11: 1
A12: 306 | B12: acnc | C12: last_delivery_date_month | D12: Last_delivery_date_month | E12: =VLOOKUP(B12&" - "&D12,OrbisGeneric_mapping!C:F,3,0) -> #N/A | F12: =VLOOKUP(E12,Collibra!D:F,3,0) -> #N/A | G12: =VLOOKUP(E12,Collibra!D:F,2,0) -> #N/A | J12: STRING | N12: FALSE | P12: 2025-08-29T13:46:54.659Z | Q12: 2025-08-29T13:46:54.663Z | R12: FALSE | Z12: 1
A13: 298 | B13: acnc | C13: last_delivery_date_year | D13: Last_delivery_date_year | E13: =VLOOKUP(B13&" - "&D13,OrbisGeneric_mapping!C:F,3,0) -> #N/A | F13: =VLOOKUP(E13,Collibra!D:F,3,0) -> #N/A | G13: =VLOOKUP(E13,Collibra!D:F,2,0) -> #N/A | J13: STRING | N13: FALSE | P13: 2025-08-29T13:46:54.659Z | Q13: 2025-08-29T13:46:54.663Z | R13: FALSE | Z13: 1
... A390: 1810 | B390: banks_global_financials_and_ratios | C390: unreserved_impaired_loans_equity_ | D390: Unreserved_impaired_loans_Equity_ | E390: =VLOOKUP(B390&" - "&D390,OrbisGeneric_mapping!C:F,3,0) -> 195070 | F390: =VLOOKUP(E390,Collibra!D:F,3,0) -> #N/A | G390: =VLOOKUP(E390,Collibra!D:F,2,0) -> #N/A | J390: STRING | N390: FALSE | P390: 2025-08-29T13:46:54.659Z | Q390: 2025-08-29T13:46:54.663Z | R390: FALSE | Z390: 1
A391: 1009 | B391: banks_global_financials_and_ratios_eur | C391: accounting_practice | D391: Accounting_practice | E391: =VLOOKUP(SUBSTITUTE(B391,"_eur","")&" - "&D391,OrbisGeneric_mapping!C:F,3,0) -> ACCOUNTING_PRACTICE | F391: =VLOOKUP(E391,Collibra!D:F,3,0) -> Accounting practice | G391: =VLOOKUP(E391,Collibra!D:F,2,0) -> <p>The accounting practice indicates the accounting standards based on which the financial accounts were prepared</p> <p>1. IFRS: IFRS (International Financial Reporting Standards) accounting practice is assigned to entities that follow accounting rules and standards issued by two standard-setting boards, the International Accounting Standards Board (IASB) and the newly created International Sustainability Standards Board. The IASB sets IFRS Accounting Standards and the ISSB sets IFRS Sustainability Disclosure Standards.</p> <p>2. IFRS – not fully complaint: IFRS – not fully complaint is assigned to entities that report financial statements based on IFRS accounting standards but has not adopted all IFRS accounting rules due to transition or exception to IFRS rule(s). </p> <p>3. Local GAAP: Local GAAP accounting practice is assigned to entities that follow the generally accepted accounting principles that are applicable in their respective jurisdictions where the company operates. E.g., Indian Accounting Standard (IND AS), Japanese GAAP</p> <p>4. US GAAP: US GAAP (United States Generally Accepted Accounting Principles) accounting practice is assigned to entities that follow the accounting rules and standards issued by the Financial Accounting Standards Board (FASB) for preparing its financial statements. </p> <p>5. Regulatory: No definition. Any local reporting should be Local GAAP.</p> | J391: STRING | N391: FALSE | P391: 2025-08-29T13:46:54.659Z | Q391: 2025-08-29T13:46:54.663Z | R391: FALSE | Z391: 1
A392: 1001 | B392: banks_global_financials_and_ratios_eur | C392: audit_status | D392: Audit_status | E392: =VLOOKUP(SUBSTITUTE(B392,"_eur","")&" - "&D392,OrbisGeneric_mapping!C:F,3,0) -> AUDIT_STATUS | F392: =VLOOKUP(E392,Collibra!D:F,3,0) -> Audit status | G392: =VLOOKUP(E392,Collibra!D:F,2,0) -> The audit status indicates the status of a statement with regard to its auditing. A financial accounts audit status could fall into qualified, unqualified, unaudited, adverse opinion, no opinion, qualification not available. This information is almost only available for publicy listed companies. | J392: STRING | N392: FALSE | P392: 2025-08-29T13:46:54.659Z | Q392: 2025-08-29T13:46:54.663Z | R392: FALSE | Z392: 1
A393: 945 | B393: banks_global_financials_and_ratios_eur | C393: bvd_id_number | D393: BvD_ID_number | E393: =VLOOKUP(SUBSTITUTE(B393,"_eur","")&" - "&D393,OrbisGeneric_mapping!C:F,3,0) -> BVD_ID_NUMBER | F393: =VLOOKUP(E393,Collibra!D:F,3,0) -> BvD ID number | G393: =VLOOKUP(E393,Collibra!D:F,2,0) -> <p class="MsoNormal"><span style="font-size: 9.0pt;font-family: Arial , sans-serif;color: rgb(11,33,44);">The BvD ID number is a company identifier that uniquely identifies each company included in at least one Bureau van Dijk product. The first two characters correspond to the ISO country code (according the ISO 3166-1 alpha-2 standard) where the company is incorporated. The rest of a BvD ID number may vary and be based on a national ID, an information provider's ID, an own internal ID.</span> As a result, BvD ID numbers may be subject to change due to changes in national IDs or an information provider's ID.</p> | J393: STRING | N393: FALSE | P393: 2025-08-29T13:46:54.659Z | Q393: 2025-08-29T13:46:54.663Z | R393: FALSE | Z393: 1
A394: 1585 | B394: banks_global_financials_and_ratios_eur | C394: cap_funds_dep_st_funding_ | D394: Cap_Funds_Dep_ST_Funding_ | E394: =VLOOKUP(SUBSTITUTE(B394,"_eur","")&" - "&D394,OrbisGeneric_mapping!C:F,3,0) -> 195160 | F394: =VLOOKUP(E394,Collibra!D:F,3,0) -> #N/A | G394: =VLOOKUP(E394,Collibra!D:F,2,0) -> #N/A | J394: STRING | N394: FALSE | P394: 2025-08-29T13:46:54.659Z | Q394: 2025-08-29T13:46:54.663Z | R394: FALSE | Z394: 1
A395: 1593 | B395: banks_global_financials_and_ratios_eur | C395: cap_funds_liabilities_ | D395: Cap_Funds_Liabilities_ | E395: =VLOOKUP(SUBSTITUTE(B395,"_eur","")&" - "&D395,OrbisGeneric_mapping!C:F,3,0) -> 195170 | F395: =VLOOKUP(E395,Collibra!D:F,3,0) -> #N/A | G395: =VLOOKUP(E395,Collibra!D:F,2,0) -> #N/A | J395: STRING | N395: FALSE | P395: 2025-08-29T13:46:54.659Z | Q395: 2025-08-29T13:46:54.663Z | R395: FALSE | Z395: 1
A396: 1577 | B396: banks_global_financials_and_ratios_eur | C396: cap_funds_net_loans_ | D396: Cap_Funds_Net_Loans_ | E396: =VLOOKUP(SUBSTITUTE(B396,"_eur","")&" - "&D396,OrbisGeneric_mapping!C:F,3,0) -> 195150 | F396: =VLOOKUP(E396,Collibra!D:F,3,0) -> #N/A | G396: =VLOOKUP(E396,Collibra!D:F,2,0) -> #N/A | J396: STRING | N396: FALSE | P396: 2025-08-29T13:46:54.659Z | Q396: 2025-08-29T13:46:54.663Z | R396: FALSE | Z396: 1
A397: 1569 | B397: banks_global_financials_and_ratios_eur | C397: cap_funds_total_assets_ | D397: Cap_Funds_Total_assets_ | E397: =VLOOKUP(SUBSTITUTE(B397,"_eur","")&" - "&D397,OrbisGeneric_mapping!C:F,3,0) -> 195140 | F397: =VLOOKUP(E397,Collibra!D:F,3,0) -> #N/A | G397: =VLOOKUP(E397,Collibra!D:F,2,0) -> #N/A | J397: STRING | N397: FALSE | P397: 2025-08-29T13:46:54.659Z | Q397: 2025-08-29T13:46:54.663Z | R397: FALSE | Z397: 1
A398: 961 | B398: banks_global_financials_and_ratios_eur | C398: closing_date | D398: Closing_date | E398: =VLOOKUP(SUBSTITUTE(B398,"_eur","")&" - "&D398,OrbisGeneric_mapping!C:F,3,0) -> CLOSING_DATE | F398: =VLOOKUP(E398,Collibra!D:F,3,0) -> Closing date | G398: =VLOOKUP(E398,Collibra!D:F,2,0) -> Closing date provides the financial accounts year or interim ending date (Default: Latest available year) | J398: STRING | N398: FALSE | P398: 2025-08-29T13:46:54.659Z | Q398: 2025-08-29T13:46:54.663Z | R398: FALSE | Z398: 1
A399: 985 | B399: banks_global_financials_and_ratios_eur | C399: closing_date_day | D399: Closing_date_day | E399: =VLOOKUP(SUBSTITUTE(B399,"_eur","")&" - "&D399,OrbisGeneric_mapping!C:F,3,0) -> #N/A | F399: =VLOOKUP(E399,Collibra!D:F,3,0) -> #N/A | G399: =VLOOKUP(E399,Collibra!D:F,2,0) -> #N/A | J399: STRING | N399: FALSE | P399: 2025-08-29T13:46:54.659Z | Q399: 2025-08-29T13:46:54.663Z | R399: FALSE | Z399: 1
A400: 977 | B400: banks_global_financials_and_ratios_eur | C400: closing_date_month | D400: Closing_date_month | E400: =VLOOKUP(SUBSTITUTE(B400,"_eur","")&" - "&D400,OrbisGeneric_mapping!C:F,3,0) -> #N/A | F400: =VLOOKUP(E400,Collibra!D:F,3,0) -> #N/A | G400: =VLOOKUP(E400,Collibra!D:F,2,0) -> #N/A | J400: STRING | N400: FALSE | P400: 2025-08-29T13:46:54.659Z | Q400: 2025-08-29T13:46:54.663Z | R400: FALSE | Z400: 1
A401: 969 | B401: banks_global_financials_and_ratios_eur | C401: closing_date_year | D401: Closing_date_year | E401: =VLOOKUP(SUBSTITUTE(B401,"_eur","")&" - "&D401,OrbisGeneric_mapping!C:F,3,0) -> #N/A | F401: =VLOOKUP(E401,Collibra!D:F,3,0) -> #N/A | G401: =VLOOKUP(E401,Collibra!D:F,2,0) -> #N/A | J401: STRING | N401: FALSE | P401: 2025-08-29T13:46:54.659Z | Q401: 2025-08-29T13:46:54.663Z | R401: FALSE | Z401: 1
A402: 953 | B402: banks_global_financials_and_ratios_eur | C402: consolidation_code | D402: Consolidation_code | E402: =VLOOKUP(SUBSTITUTE(B402,"_eur","")&" - "&D402,OrbisGeneric_mapping!C:F,3,0) -> CONSOLIDATION_CODE | F402: =VLOOKUP(E402,Collibra!D:F,3,0) -> Consolidation code | G402: =VLOOKUP(E402,Collibra!D:F,2,0) -> <p>Consolidation code defines whether a financial statement is Consolidated or Unconsolidated. Based on the number of financials statements published in a report, a numeric suffix is added (C1, C2, U1 and U2) to distinguish the reports available between various entities. Suffix 1 refers the entity publishes consolidated/unconsolidated only while suffix 2 represents the entity publishes both Consolidated and Unconsolidated in the same report. Similarly, to distinguish availability of additional consolidated or unconsolidated statement suffix * is added (C* and U*). Additional financial statements appears if the entity has different accounting standard or more than one source.</p> <p>Companies with limited financial data are those with a consolidation code of LF (limited financials). The information available for such companies is often based on rounded figures - or class level - officially available (sometimes also collected from other directories or web sites). In most cases only “Number of employees” and “Operating Revenue” are available. There are several countries where detailed financials are not available for some companies. In such cases, LF are quite often made of median value of revenue range (or estimate), median value of employee range (or estimate) and current capital. Figures are reported for the current year (when recently collected and reflecting latest situation) such as YYYY. Figures might change during the course of Year YYYY until 31/12/YYYY when they are fixed and new figures are reported for Year YYYY+1.</p> | J402: STRING | N402: FALSE | P402: 2025-08-29T13:46:54.659Z | Q402: 2025-08-29T13:46:54.663Z | R402: FALSE | Z402: 1
... A508: 1505 | B508: banks_global_financials_and_ratios_eur | C508: unreserved_impaired_loans_equity_ | D508: Unreserved_impaired_loans_Equity_ | E508: =VLOOKUP(SUBSTITUTE(B508,"_eur","")&" - "&D508,OrbisGeneric_mapping!C:F,3,0) -> 195070 | F508: =VLOOKUP(E508,Collibra!D:F,3,0) -> #N/A | G508: =VLOOKUP(E508,Collibra!D:F,2,0) -> #N/A | J508: STRING | N508: FALSE | P508: 2025-08-29T13:46:54.659Z | Q508: 2025-08-29T13:46:54.663Z | R508: FALSE | Z508: 1
A509: 2633 | B509: banks_global_financials_and_ratios_eur_interim | C509: accounting_practice | D509: Accounting_practice | E509: =VLOOKUP(B509&" - "&D509,OrbisGeneric_mapping!C:F,3,0) -> ACCOUNTING_PRACTICE | F509: =VLOOKUP(E509,Collibra!D:F,3,0) -> Accounting practice | G509: =VLOOKUP(E509,Collibra!D:F,2,0) -> <p>The accounting practice indicates the accounting standards based on which the financial accounts were prepared</p> <p>1. IFRS: IFRS (International Financial Reporting Standards) accounting practice is assigned to entities that follow accounting rules and standards issued by two standard-setting boards, the International Accounting Standards Board (IASB) and the newly created International Sustainability Standards Board. The IASB sets IFRS Accounting Standards and the ISSB sets IFRS Sustainability Disclosure Standards.</p> <p>2. IFRS – not fully complaint: IFRS – not fully complaint is assigned to entities that report financial statements based on IFRS accounting standards but has not adopted all IFRS accounting rules due to transition or exception to IFRS rule(s). </p> <p>3. Local GAAP: Local GAAP accounting practice is assigned to entities that follow the generally accepted accounting principles that are applicable in their respective jurisdictions where the company operates. E.g., Indian Accounting Standard (IND AS), Japanese GAAP</p> <p>4. US GAAP: US GAAP (United States Generally Accepted Accounting Principles) accounting practice is assigned to entities that follow the accounting rules and standards issued by the Financial Accounting Standards Board (FASB) for preparing its financial statements. </p> <p>5. Regulatory: No definition. Any local reporting should be Local GAAP.</p> | J509: STRING | N509: FALSE | P509: 2025-08-29T13:46:54.659Z | Q509: 2025-08-29T13:46:54.663Z | R509: FALSE | Z509: 1
A510: 2625 | B510: banks_global_financials_and_ratios_eur_interim | C510: audit_status | D510: Audit_status | E510: =VLOOKUP(B510&" - "&D510,OrbisGeneric_mapping!C:F,3,0) -> AUDIT_STATUS | F510: =VLOOKUP(E510,Collibra!D:F,3,0) -> Audit status | G510: =VLOOKUP(E510,Collibra!D:F,2,0) -> The audit status indicates the status of a statement with regard to its auditing. A financial accounts audit status could fall into qualified, unqualified, unaudited, adverse opinion, no opinion, qualification not available. This information is almost only available for publicy listed companies. | J510: STRING | N510: FALSE | P510: 2025-08-29T13:46:54.659Z | Q510: 2025-08-29T13:46:54.663Z | R510: FALSE | Z510: 1
A511: 2569 | B511: banks_global_financials_and_ratios_eur_interim | C511: bvd_id_number | D511: BvD_ID_number | E511: =VLOOKUP(B511&" - "&D511,OrbisGeneric_mapping!C:F,3,0) -> BVD_ID_NUMBER | F511: =VLOOKUP(E511,Collibra!D:F,3,0) -> BvD ID number | G511: =VLOOKUP(E511,Collibra!D:F,2,0) -> <p class="MsoNormal"><span style="font-size: 9.0pt;font-family: Arial , sans-serif;color: rgb(11,33,44);">The BvD ID number is a company identifier that uniquely identifies each company included in at least one Bureau van Dijk product. The first two characters correspond to the ISO country code (according the ISO 3166-1 alpha-2 standard) where the company is incorporated. The rest of a BvD ID number may vary and be based on a national ID, an information provider's ID, an own internal ID.</span> As a result, BvD ID numbers may be subject to change due to changes in national IDs or an information provider's ID.</p> | J511: STRING | N511: FALSE | P511: 2025-08-29T13:46:54.659Z | Q511: 2025-08-29T13:46:54.663Z | R511: FALSE | Z511: 1
A512: 3209 | B512: banks_global_financials_and_ratios_eur_interim | C512: cap_funds_dep_st_funding_ | D512: Cap_Funds_Dep_ST_Funding_ | E512: =VLOOKUP(B512&" - "&D512,OrbisGeneric_mapping!C:F,3,0) -> 195160 | F512: =VLOOKUP(E512,Collibra!D:F,3,0) -> #N/A | G512: =VLOOKUP(E512,Collibra!D:F,2,0) -> #N/A | J512: STRING | N512: FALSE | P512: 2025-08-29T13:46:54.659Z | Q512: 2025-08-29T13:46:54.663Z | R512: FALSE | Z512: 1
A513: 3217 | B513: banks_global_financials_and_ratios_eur_interim | C513: cap_funds_liabilities_ | D513: Cap_Funds_Liabilities_ | E513: =VLOOKUP(B513&" - "&D513,OrbisGeneric_mapping!C:F,3,0) -> 195170 | F513: =VLOOKUP(E513,Collibra!D:F,3,0) -> #N/A | G513: =VLOOKUP(E513,Collibra!D:F,2,0) -> #N/A | J513: STRING | N513: FALSE | P513: 2025-08-29T13:46:54.659Z | Q513: 2025-08-29T13:46:54.663Z | R513: FALSE | Z513: 1
A514: 3201 | B514: banks_global_financials_and_ratios_eur_interim | C514: cap_funds_net_loans_ | D514: Cap_Funds_Net_Loans_ | E514: =VLOOKUP(B514&" - "&D514,OrbisGeneric_mapping!C:F,3,0) -> 195150 | F514: =VLOOKUP(E514,Collibra!D:F,3,0) -> #N/A | G514: =VLOOKUP(E514,Collibra!D:F,2,0) -> #N/A | J514: STRING | N514: FALSE | P514: 2025-08-29T13:46:54.659Z | Q514: 2025-08-29T13:46:54.663Z | R514: FALSE | Z514: 1
A515: 3193 | B515: banks_global_financials_and_ratios_eur_interim | C515: cap_funds_total_assets_ | D515: Cap_Funds_Total_assets_ | E515: =VLOOKUP(B515&" - "&D515,OrbisGeneric_mapping!C:F,3,0) -> 195140 | F515: =VLOOKUP(E515,Collibra!D:F,3,0) -> #N/A | G515: =VLOOKUP(E515,Collibra!D:F,2,0) -> #N/A | J515: STRING | N515: FALSE | P515: 2025-08-29T13:46:54.659Z | Q515: 2025-08-29T13:46:54.663Z | R515: FALSE | Z515: 1
A516: 2585 | B516: banks_global_financials_and_ratios_eur_interim | C516: closing_date | D516: Closing_date | E516: =VLOOKUP(B516&" - "&D516,OrbisGeneric_mapping!C:F,3,0) -> CLOSING_DATE | F516: =VLOOKUP(E516,Collibra!D:F,3,0) -> Closing date | G516: =VLOOKUP(E516,Collibra!D:F,2,0) -> Closing date provides the financial accounts year or interim ending date (Default: Latest available year) | J516: STRING | N516: FALSE | P516: 2025-08-29T13:46:54.659Z | Q516: 2025-08-29T13:46:54.663Z | R516: FALSE | Z516: 1
A517: 2609 | B517: banks_global_financials_and_ratios_eur_interim | C517: closing_date_day | D517: Closing_date_day | E517: =VLOOKUP(B517&" - "&D517,OrbisGeneric_mapping!C:F,3,0) -> #N/A | F517: =VLOOKUP(E517,Collibra!D:F,3,0) -> #N/A | G517: =VLOOKUP(E517,Collibra!D:F,2,0) -> #N/A | J517: STRING | N517: FALSE | P517: 2025-08-29T13:46:54.659Z | Q517: 2025-08-29T13:46:54.663Z | R517: FALSE | Z517: 1
A518: 2601 | B518: banks_global_financials_and_ratios_eur_interim | C518: closing_date_month | D518: Closing_date_month | E518: =VLOOKUP(B518&" - "&D518,OrbisGeneric_mapping!C:F,3,0) -> #N/A | F518: =VLOOKUP(E518,Collibra!D:F,3,0) -> #N/A | G518: =VLOOKUP(E518,Collibra!D:F,2,0) -> #N/A | J518: STRING | N518: FALSE | P518: 2025-08-29T13:46:54.659Z | Q518: 2025-08-29T13:46:54.663Z | R518: FALSE | Z518: 1
A519: 2593 | B519: banks_global_financials_and_ratios_eur_interim | C519: closing_date_year | D519: Closing_date_year | E519: =VLOOKUP(B519&" - "&D519,OrbisGeneric_mapping!C:F,3,0) -> #N/A | F519: =VLOOKUP(E519,Collibra!D:F,3,0) -> #N/A | G519: =VLOOKUP(E519,Collibra!D:F,2,0) -> #N/A | J519: STRING | N519: FALSE | P519: 2025-08-29T13:46:54.659Z | Q519: 2025-08-29T13:46:54.663Z | R519: FALSE | Z519: 1
A520: 2577 | B520: banks_global_financials_and_ratios_eur_interim | C520: consolidation_code | D520: Consolidation_code | E520: =VLOOKUP(B520&" - "&D520,OrbisGeneric_mapping!C:F,3,0) -> CONSOLIDATION_CODE | F520: =VLOOKUP(E520,Collibra!D:F,3,0) -> Consolidation code | G520: =VLOOKUP(E520,Collibra!D:F,2,0) -> <p>Consolidation code defines whether a financial statement is Consolidated or Unconsolidated. Based on the number of financials statements published in a report, a numeric suffix is added (C1, C2, U1 and U2) to distinguish the reports available between various entities. Suffix 1 refers the entity publishes consolidated/unconsolidated only while suffix 2 represents the entity publishes both Consolidated and Unconsolidated in the same report. Similarly, to distinguish availability of additional consolidated or unconsolidated statement suffix * is added (C* and U*). Additional financial statements appears if the entity has different accounting standard or more than one source.</p> <p>Companies with limited financial data are those with a consolidation code of LF (limited financials). The information available for such companies is often based on rounded figures - or class level - officially available (sometimes also collected from other directories or web sites). In most cases only “Number of employees” and “Operating Revenue” are available. There are several countries where detailed financials are not available for some companies. In such cases, LF are quite often made of median value of revenue range (or estimate), median value of employee range (or estimate) and current capital. Figures are reported for the current year (when recently collected and reflecting latest situation) such as YYYY. Figures might change during the course of Year YYYY until 31/12/YYYY when they are fixed and new figures are reported for Year YYYY+1.</p> | J520: STRING | N520: FALSE | P520: 2025-08-29T13:46:54.659Z | Q520: 2025-08-29T13:46:54.663Z | R520: FALSE | Z520: 1
... A627: 3129 | B627: banks_global_financials_and_ratios_eur_interim | C627: unreserved_impaired_loans_equity_ | D627: Unreserved_impaired_loans_Equity_ | E627: =VLOOKUP(B627&" - "&D627,OrbisGeneric_mapping!C:F,3,0) -> 195070 | F627: =VLOOKUP(E627,Collibra!D:F,3,0) -> #N/A | G627: =VLOOKUP(E627,Collibra!D:F,2,0) -> #N/A | J627: STRING | N627: FALSE | P627: 2025-08-29T13:46:54.659Z | Q627: 2025-08-29T13:46:54.663Z | R627: FALSE | Z627: 1
A628: 533 | B628: banks_global_financials_and_ratios_interim | C628: accounting_practice | D628: Accounting_practice | E628: =VLOOKUP(SUBSTITUTE(B628,"_interim","_EUR_interim")&" - "&D628,OrbisGeneric_mapping!C:F,3,0) -> ACCOUNTING_PRACTICE | F628: =VLOOKUP(E628,Collibra!D:F,3,0) -> Accounting practice | G628: =VLOOKUP(E628,Collibra!D:F,2,0) -> <p>The accounting practice indicates the accounting standards based on which the financial accounts were prepared</p> <p>1. IFRS: IFRS (International Financial Reporting Standards) accounting practice is assigned to entities that follow accounting rules and standards issued by two standard-setting boards, the International Accounting Standards Board (IASB) and the newly created International Sustainability Standards Board. The IASB sets IFRS Accounting Standards and the ISSB sets IFRS Sustainability Disclosure Standards.</p> <p>2. IFRS – not fully complaint: IFRS – not fully complaint is assigned to entities that report financial statements based on IFRS accounting standards but has not adopted all IFRS accounting rules due to transition or exception to IFRS rule(s). </p> <p>3. Local GAAP: Local GAAP accounting practice is assigned to entities that follow the generally accepted accounting principles that are applicable in their respective jurisdictions where the company operates. E.g., Indian Accounting Standard (IND AS), Japanese GAAP</p> <p>4. US GAAP: US GAAP (United States Generally Accepted Accounting Principles) accounting practice is assigned to entities that follow the accounting rules and standards issued by the Financial Accounting Standards Board (FASB) for preparing its financial statements. </p> <p>5. Regulatory: No definition. Any local reporting should be Local GAAP.</p> | J628: STRING | N628: FALSE | P628: 2025-08-29T13:46:54.659Z | Q628: 2025-08-29T13:46:54.663Z | R628: FALSE | Z628: 1
A629: 525 | B629: banks_global_financials_and_ratios_interim | C629: audit_status | D629: Audit_status | E629: =VLOOKUP(SUBSTITUTE(B629,"_interim","_EUR_interim")&" - "&D629,OrbisGeneric_mapping!C:F,3,0) -> AUDIT_STATUS | F629: =VLOOKUP(E629,Collibra!D:F,3,0) -> Audit status | G629: =VLOOKUP(E629,Collibra!D:F,2,0) -> The audit status indicates the status of a statement with regard to its auditing. A financial accounts audit status could fall into qualified, unqualified, unaudited, adverse opinion, no opinion, qualification not available. This information is almost only available for publicy listed companies. | J629: STRING | N629: FALSE | P629: 2025-08-29T13:46:54.659Z | Q629: 2025-08-29T13:46:54.663Z | R629: FALSE | Z629: 1
A630: 469 | B630: banks_global_financials_and_ratios_interim | C630: bvd_id_number | D630: BvD_ID_number | E630: =VLOOKUP(SUBSTITUTE(B630,"_interim","_EUR_interim")&" - "&D630,OrbisGeneric_mapping!C:F,3,0) -> BVD_ID_NUMBER | F630: =VLOOKUP(E630,Collibra!D:F,3,0) -> BvD ID number | G630: =VLOOKUP(E630,Collibra!D:F,2,0) -> <p class="MsoNormal"><span style="font-size: 9.0pt;font-family: Arial , sans-serif;color: rgb(11,33,44);">The BvD ID number is a company identifier that uniquely identifies each company included in at least one Bureau van Dijk product. The first two characters correspond to the ISO country code (according the ISO 3166-1 alpha-2 standard) where the company is incorporated. The rest of a BvD ID number may vary and be based on a national ID, an information provider's ID, an own internal ID.</span> As a result, BvD ID numbers may be subject to change due to changes in national IDs or an information provider's ID.</p> | J630: STRING | N630: FALSE | P630: 2025-08-29T13:46:54.659Z | Q630: 2025-08-29T13:46:54.663Z | R630: FALSE | Z630: 1
A631: 1101 | B631: banks_global_financials_and_ratios_interim | C631: cap_funds_dep_st_funding_ | D631: Cap_Funds_Dep_ST_Funding_ | E631: =VLOOKUP(SUBSTITUTE(B631,"_interim","_EUR_interim")&" - "&D631,OrbisGeneric_mapping!C:F,3,0) -> 195160 | F631: =VLOOKUP(E631,Collibra!D:F,3,0) -> #N/A | G631: =VLOOKUP(E631,Collibra!D:F,2,0) -> #N/A | J631: STRING | N631: FALSE | P631: 2025-08-29T13:46:54.659Z | Q631: 2025-08-29T13:46:54.663Z | R631: FALSE | Z631: 1
A632: 1109 | B632: banks_global_financials_and_ratios_interim | C632: cap_funds_liabilities_ | D632: Cap_Funds_Liabilities_ | E632: =VLOOKUP(SUBSTITUTE(B632,"_interim","_EUR_interim")&" - "&D632,OrbisGeneric_mapping!C:F,3,0) -> 195170 | F632: =VLOOKUP(E632,Collibra!D:F,3,0) -> #N/A | G632: =VLOOKUP(E632,Collibra!D:F,2,0) -> #N/A | J632: STRING | N632: FALSE | P632: 2025-08-29T13:46:54.659Z | Q632: 2025-08-29T13:46:54.663Z | R632: FALSE | Z632: 1
A633: 1093 | B633: banks_global_financials_and_ratios_interim | C633: cap_funds_net_loans_ | D633: Cap_Funds_Net_Loans_ | E633: =VLOOKUP(SUBSTITUTE(B633,"_interim","_EUR_interim")&" - "&D633,OrbisGeneric_mapping!C:F,3,0) -> 195150 | F633: =VLOOKUP(E633,Collibra!D:F,3,0) -> #N/A | G633: =VLOOKUP(E633,Collibra!D:F,2,0) -> #N/A | J633: STRING | N633: FALSE | P633: 2025-08-29T13:46:54.659Z | Q633: 2025-08-29T13:46:54.663Z | R633: FALSE | Z633: 1
A634: 1085 | B634: banks_global_financials_and_ratios_interim | C634: cap_funds_total_assets_ | D634: Cap_Funds_Total_assets_ | E634: =VLOOKUP(SUBSTITUTE(B634,"_interim","_EUR_interim")&" - "&D634,OrbisGeneric_mapping!C:F,3,0) -> 195140 | F634: =VLOOKUP(E634,Collibra!D:F,3,0) -> #N/A | G634: =VLOOKUP(E634,Collibra!D:F,2,0) -> #N/A | J634: STRING | N634: FALSE | P634: 2025-08-29T13:46:54.659Z | Q634: 2025-08-29T13:46:54.663Z | R634: FALSE | Z634: 1
A635: 485 | B635: banks_global_financials_and_ratios_interim | C635: closing_date | D635: Closing_date | E635: =VLOOKUP(SUBSTITUTE(B635,"_interim","_EUR_interim")&" - "&D635,OrbisGeneric_mapping!C:F,3,0) -> CLOSING_DATE | F635: =VLOOKUP(E635,Collibra!D:F,3,0) -> Closing date | G635: =VLOOKUP(E635,Collibra!D:F,2,0) -> Closing date provides the financial accounts year or interim ending date (Default: Latest available year) | J635: STRING | N635: FALSE | P635: 2025-08-29T13:46:54.659Z | Q635: 2025-08-29T13:46:54.663Z | R635: FALSE | Z635: 1
A636: 509 | B636: banks_global_financials_and_ratios_interim | C636: closing_date_day | D636: Closing_date_day | E636: =VLOOKUP(SUBSTITUTE(B636,"_interim","_EUR_interim")&" - "&D636,OrbisGeneric_mapping!C:F,3,0) -> #N/A | F636: =VLOOKUP(E636,Collibra!D:F,3,0) -> #N/A | G636: =VLOOKUP(E636,Collibra!D:F,2,0) -> #N/A | J636: STRING | N636: FALSE | P636: 2025-08-29T13:46:54.659Z | Q636: 2025-08-29T13:46:54.663Z | R636: FALSE | Z636: 1
A637: 501 | B637: banks_global_financials_and_ratios_interim | C637: closing_date_month | D637: Closing_date_month | E637: =VLOOKUP(SUBSTITUTE(B637,"_interim","_EUR_interim")&" - "&D637,OrbisGeneric_mapping!C:F,3,0) -> #N/A | F637: =VLOOKUP(E637,Collibra!D:F,3,0) -> #N/A | G637: =VLOOKUP(E637,Collibra!D:F,2,0) -> #N/A | J637: STRING | N637: FALSE | P637: 2025-08-29T13:46:54.659Z | Q637: 2025-08-29T13:46:54.663Z | R637: FALSE | Z637: 1
A638: 493 | B638: banks_global_financials_and_ratios_interim | C638: closing_date_year | D638: Closing_date_year | E638: =VLOOKUP(SUBSTITUTE(B638,"_interim","_EUR_interim")&" - "&D638,OrbisGeneric_mapping!C:F,3,0) -> #N/A | F638: =VLOOKUP(E638,Collibra!D:F,3,0) -> #N/A | G638: =VLOOKUP(E638,Collibra!D:F,2,0) -> #N/A | J638: STRING | N638: FALSE | P638: 2025-08-29T13:46:54.659Z | Q638: 2025-08-29T13:46:54.663Z | R638: FALSE | Z638: 1
A639: 477 | B639: banks_global_financials_and_ratios_interim | C639: consolidation_code | D639: Consolidation_code | E639: =VLOOKUP(SUBSTITUTE(B639,"_interim","_EUR_interim")&" - "&D639,OrbisGeneric_mapping!C:F,3,0) -> CONSOLIDATION_CODE | F639: =VLOOKUP(E639,Collibra!D:F,3,0) -> Consolidation code | G639: =VLOOKUP(E639,Collibra!D:F,2,0) -> <p>Consolidation code defines whether a financial statement is Consolidated or Unconsolidated. Based on the number of financials statements published in a report, a numeric suffix is added (C1, C2, U1 and U2) to distinguish the reports available between various entities. Suffix 1 refers the entity publishes consolidated/unconsolidated only while suffix 2 represents the entity publishes both Consolidated and Unconsolidated in the same report. Similarly, to distinguish availability of additional consolidated or unconsolidated statement suffix * is added (C* and U*). Additional financial statements appears if the entity has different accounting standard or more than one source.</p> <p>Companies with limited financial data are those with a consolidation code of LF (limited financials). The information available for such companies is often based on rounded figures - or class level - officially available (sometimes also collected from other directories or web sites). In most cases only “Number of employees” and “Operating Revenue” are available. There are several countries where detailed financials are not available for some companies. In such cases, LF are quite often made of median value of revenue range (or estimate), median value of employee range (or estimate) and current capital. Figures are reported for the current year (when recently collected and reflecting latest situation) such as YYYY. Figures might change during the course of Year YYYY until 31/12/YYYY when they are fixed and new figures are reported for Year YYYY+1.</p> | J639: STRING | N639: FALSE | P639: 2025-08-29T13:46:54.659Z | Q639: 2025-08-29T13:46:54.663Z | R639: FALSE | Z639: 1
... A745: 1021 | B745: banks_global_financials_and_ratios_interim | C745: unreserved_impaired_loans_equity_ | D745: Unreserved_impaired_loans_Equity_ | E745: =VLOOKUP(SUBSTITUTE(B745,"_interim","_EUR_interim")&" - "&D745,OrbisGeneric_mapping!C:F,3,0) -> 195070 | F745: =VLOOKUP(E745,Collibra!D:F,3,0) -> #N/A | G745: =VLOOKUP(E745,Collibra!D:F,2,0) -> #N/A | J745: STRING | N745: FALSE | P745: 2025-08-29T13:46:54.659Z | Q745: 2025-08-29T13:46:54.663Z | R745: FALSE | Z745: 1
A746: 2714 | B746: banks_global_financials_and_ratios_usd | C746: accounting_practice | D746: Accounting_practice | E746: =VLOOKUP(SUBSTITUTE(B746,"_usd","")&" - "&D746,OrbisGeneric_mapping!C:F,3,0) -> ACCOUNTING_PRACTICE | F746: =VLOOKUP(E746,Collibra!D:F,3,0) -> Accounting practice | G746: =VLOOKUP(E746,Collibra!D:F,2,0) -> <p>The accounting practice indicates the accounting standards based on which the financial accounts were prepared</p> <p>1. IFRS: IFRS (International Financial Reporting Standards) accounting practice is assigned to entities that follow accounting rules and standards issued by two standard-setting boards, the International Accounting Standards Board (IASB) and the newly created International Sustainability Standards Board. The IASB sets IFRS Accounting Standards and the ISSB sets IFRS Sustainability Disclosure Standards.</p> <p>2. IFRS – not fully complaint: IFRS – not fully complaint is assigned to entities that report financial statements based on IFRS accounting standards but has not adopted all IFRS accounting rules due to transition or exception to IFRS rule(s). </p> <p>3. Local GAAP: Local GAAP accounting practice is assigned to entities that follow the generally accepted accounting principles that are applicable in their respective jurisdictions where the company operates. E.g., Indian Accounting Standard (IND AS), Japanese GAAP</p> <p>4. US GAAP: US GAAP (United States Generally Accepted Accounting Principles) accounting practice is assigned to entities that follow the accounting rules and standards issued by the Financial Accounting Standards Board (FASB) for preparing its financial statements. </p> <p>5. Regulatory: No definition. Any local reporting should be Local GAAP.</p> | J746: STRING | N746: FALSE | P746: 2025-08-29T13:46:54.659Z | Q746: 2025-08-29T13:46:54.663Z | R746: FALSE | Z746: 1
A747: 2706 | B747: banks_global_financials_and_ratios_usd | C747: audit_status | D747: Audit_status | E747: =VLOOKUP(SUBSTITUTE(B747,"_usd","")&" - "&D747,OrbisGeneric_mapping!C:F,3,0) -> AUDIT_STATUS | F747: =VLOOKUP(E747,Collibra!D:F,3,0) -> Audit status | G747: =VLOOKUP(E747,Collibra!D:F,2,0) -> The audit status indicates the status of a statement with regard to its auditing. A financial accounts audit status could fall into qualified, unqualified, unaudited, adverse opinion, no opinion, qualification not available. This information is almost only available for publicy listed companies. | J747: STRING | N747: FALSE | P747: 2025-08-29T13:46:54.659Z | Q747: 2025-08-29T13:46:54.663Z | R747: FALSE | Z747: 1
A748: 2650 | B748: banks_global_financials_and_ratios_usd | C748: bvd_id_number | D748: BvD_ID_number | E748: =VLOOKUP(SUBSTITUTE(B748,"_usd","")&" - "&D748,OrbisGeneric_mapping!C:F,3,0) -> BVD_ID_NUMBER | F748: =VLOOKUP(E748,Collibra!D:F,3,0) -> BvD ID number | G748: =VLOOKUP(E748,Collibra!D:F,2,0) -> <p class="MsoNormal"><span style="font-size: 9.0pt;font-family: Arial , sans-serif;color: rgb(11,33,44);">The BvD ID number is a company identifier that uniquely identifies each company included in at least one Bureau van Dijk product. The first two characters correspond to the ISO country code (according the ISO 3166-1 alpha-2 standard) where the company is incorporated. The rest of a BvD ID number may vary and be based on a national ID, an information provider's ID, an own internal ID.</span> As a result, BvD ID numbers may be subject to change due to changes in national IDs or an information provider's ID.</p> | J748: STRING | N748: FALSE | P748: 2025-08-29T13:46:54.659Z | Q748: 2025-08-29T13:46:54.663Z | R748: FALSE | Z748: 1
A749: 3290 | B749: banks_global_financials_and_ratios_usd | C749: cap_funds_dep_st_funding_ | D749: Cap_Funds_Dep_ST_Funding_ | E749: =VLOOKUP(SUBSTITUTE(B749,"_usd","")&" - "&D749,OrbisGeneric_mapping!C:F,3,0) -> 195160 | F749: =VLOOKUP(E749,Collibra!D:F,3,0) -> #N/A | G749: =VLOOKUP(E749,Collibra!D:F,2,0) -> #N/A | J749: STRING | N749: FALSE | P749: 2025-08-29T13:46:54.659Z | Q749: 2025-08-29T13:46:54.663Z | R749: FALSE | Z749: 1
A750: 3298 | B750: banks_global_financials_and_ratios_usd | C750: cap_funds_liabilities_ | D750: Cap_Funds_Liabilities_ | E750: =VLOOKUP(SUBSTITUTE(B750,"_usd","")&" - "&D750,OrbisGeneric_mapping!C:F,3,0) -> 195170 | F750: =VLOOKUP(E750,Collibra!D:F,3,0) -> #N/A | G750: =VLOOKUP(E750,Collibra!D:F,2,0) -> #N/A | J750: STRING | N750: FALSE | P750: 2025-08-29T13:46:54.659Z | Q750: 2025-08-29T13:46:54.663Z | R750: FALSE | Z750: 1
A751: 3282 | B751: banks_global_financials_and_ratios_usd | C751: cap_funds_net_loans_ | D751: Cap_Funds_Net_Loans_ | E751: =VLOOKUP(SUBSTITUTE(B751,"_usd","")&" - "&D751,OrbisGeneric_mapping!C:F,3,0) -> 195150 | F751: =VLOOKUP(E751,Collibra!D:F,3,0) -> #N/A | G751: =VLOOKUP(E751,Collibra!D:F,2,0) -> #N/A | J751: STRING | N751: FALSE | P751: 2025-08-29T13:46:54.659Z | Q751: 2025-08-29T13:46:54.663Z | R751: FALSE | Z751: 1
A752: 3274 | B752: banks_global_financials_and_ratios_usd | C752: cap_funds_total_assets_ | D752: Cap_Funds_Total_assets_ | E752: =VLOOKUP(SUBSTITUTE(B752,"_usd","")&" - "&D752,OrbisGeneric_mapping!C:F,3,0) -> 195140 | F752: =VLOOKUP(E752,Collibra!D:F,3,0) -> #N/A | G752: =VLOOKUP(E752,Collibra!D:F,2,0) -> #N/A | J752: STRING | N752: FALSE | P752: 2025-08-29T13:46:54.659Z | Q752: 2025-08-29T13:46:54.663Z | R752: FALSE | Z752: 1
A753: 2666 | B753: banks_global_financials_and_ratios_usd | C753: closing_date | D753: Closing_date | E753: =VLOOKUP(SUBSTITUTE(B753,"_usd","")&" - "&D753,OrbisGeneric_mapping!C:F,3,0) -> CLOSING_DATE | F753: =VLOOKUP(E753,Collibra!D:F,3,0) -> Closing date | G753: =VLOOKUP(E753,Collibra!D:F,2,0) -> Closing date provides the financial accounts year or interim ending date (Default: Latest available year) | J753: STRING | N753: FALSE | P753: 2025-08-29T13:46:54.659Z | Q753: 2025-08-29T13:46:54.663Z | R753: FALSE | Z753: 1
A754: 2690 | B754: banks_global_financials_and_ratios_usd | C754: closing_date_day | D754: Closing_date_day | E754: =VLOOKUP(SUBSTITUTE(B754,"_usd","")&" - "&D754,OrbisGeneric_mapping!C:F,3,0) -> #N/A | F754: =VLOOKUP(E754,Collibra!D:F,3,0) -> #N/A | G754: =VLOOKUP(E754,Collibra!D:F,2,0) -> #N/A | J754: STRING | N754: FALSE | P754: 2025-08-29T13:46:54.659Z | Q754: 2025-08-29T13:46:54.663Z | R754: FALSE | Z754: 1
A755: 2682 | B755: banks_global_financials_and_ratios_usd | C755: closing_date_month | D755: Closing_date_month | E755: =VLOOKUP(SUBSTITUTE(B755,"_usd","")&" - "&D755,OrbisGeneric_mapping!C:F,3,0) -> #N/A | F755: =VLOOKUP(E755,Collibra!D:F,3,0) -> #N/A | G755: =VLOOKUP(E755,Collibra!D:F,2,0) -> #N/A | J755: STRING | N755: FALSE | P755: 2025-08-29T13:46:54.659Z | Q755: 2025-08-29T13:46:54.663Z | R755: FALSE | Z755: 1
A756: 2674 | B756: banks_global_financials_and_ratios_usd | C756: closing_date_year | D756: Closing_date_year | E756: =VLOOKUP(SUBSTITUTE(B756,"_usd","")&" - "&D756,OrbisGeneric_mapping!C:F,3,0) -> #N/A | F756: =VLOOKUP(E756,Collibra!D:F,3,0) -> #N/A | G756: =VLOOKUP(E756,Collibra!D:F,2,0) -> #N/A | J756: STRING | N756: FALSE | P756: 2025-08-29T13:46:54.659Z | Q756: 2025-08-29T13:46:54.663Z | R756: FALSE | Z756: 1
A757: 2658 | B757: banks_global_financials_and_ratios_usd | C757: consolidation_code | D757: Consolidation_code | E757: =VLOOKUP(SUBSTITUTE(B757,"_usd","")&" - "&D757,OrbisGeneric_mapping!C:F,3,0) -> CONSOLIDATION_CODE | F757: =VLOOKUP(E757,Collibra!D:F,3,0) -> Consolidation code | G757: =VLOOKUP(E757,Collibra!D:F,2,0) -> <p>Consolidation code defines whether a financial statement is Consolidated or Unconsolidated. Based on the number of financials statements published in a report, a numeric suffix is added (C1, C2, U1 and U2) to distinguish the reports available between various entities. Suffix 1 refers the entity publishes consolidated/unconsolidated only while suffix 2 represents the entity publishes both Consolidated and Unconsolidated in the same report. Similarly, to distinguish availability of additional consolidated or unconsolidated statement suffix * is added (C* and U*). Additional financial statements appears if the entity has different accounting standard or more than one source.</p> <p>Companies with limited financial data are those with a consolidation code of LF (limited financials). The information available for such companies is often based on rounded figures - or class level - officially available (sometimes also collected from other directories or web sites). In most cases only “Number of employees” and “Operating Revenue” are available. There are several countries where detailed financials are not available for some companies. In such cases, LF are quite often made of median value of revenue range (or estimate), median value of employee range (or estimate) and current capital. Figures are reported for the current year (when recently collected and reflecting latest situation) such as YYYY. Figures might change during the course of Year YYYY until 31/12/YYYY when they are fixed and new figures are reported for Year YYYY+1.</p> | J757: STRING | N757: FALSE | P757: 2025-08-29T13:46:54.659Z | Q757: 2025-08-29T13:46:54.663Z | R757: FALSE | Z757: 1
... A863: 3210 | B863: banks_global_financials_and_ratios_usd | C863: unreserved_impaired_loans_equity_ | D863: Unreserved_impaired_loans_Equity_ | E863: =VLOOKUP(SUBSTITUTE(B863,"_usd","")&" - "&D863,OrbisGeneric_mapping!C:F,3,0) -> 195070 | F863: =VLOOKUP(E863,Collibra!D:F,3,0) -> #N/A | G863: =VLOOKUP(E863,Collibra!D:F,2,0) -> #N/A | J863: STRING | N863: FALSE | P863: 2025-08-29T13:46:54.659Z | Q863: 2025-08-29T13:46:54.663Z | R863: FALSE | Z863: 1
A864: 3787 | B864: banks_global_financials_and_ratios_usd_interim | C864: accounting_practice | D864: Accounting_practice | E864: =VLOOKUP(SUBSTITUTE(B864,"_usd_","_eur_")&" - "&D864,OrbisGeneric_mapping!C:F,3,0) -> ACCOUNTING_PRACTICE | F864: =VLOOKUP(E864,Collibra!D:F,3,0) -> Accounting practice | G864: =VLOOKUP(E864,Collibra!D:F,2,0) -> <p>The accounting practice indicates the accounting standards based on which the financial accounts were prepared</p> <p>1. IFRS: IFRS (International Financial Reporting Standards) accounting practice is assigned to entities that follow accounting rules and standards issued by two standard-setting boards, the International Accounting Standards Board (IASB) and the newly created International Sustainability Standards Board. The IASB sets IFRS Accounting Standards and the ISSB sets IFRS Sustainability Disclosure Standards.</p> <p>2. IFRS – not fully complaint: IFRS – not fully complaint is assigned to entities that report financial statements based on IFRS accounting standards but has not adopted all IFRS accounting rules due to transition or exception to IFRS rule(s). </p> <p>3. Local GAAP: Local GAAP accounting practice is assigned to entities that follow the generally accepted accounting principles that are applicable in their respective jurisdictions where the company operates. E.g., Indian Accounting Standard (IND AS), Japanese GAAP</p> <p>4. US GAAP: US GAAP (United States Generally Accepted Accounting Principles) accounting practice is assigned to entities that follow the accounting rules and standards issued by the Financial Accounting Standards Board (FASB) for preparing its financial statements. </p> <p>5. Regulatory: No definition. Any local reporting should be Local GAAP.</p> | J864: STRING | N864: FALSE | P864: 2025-08-29T13:46:54.659Z | Q864: 2025-08-29T13:46:54.663Z | R864: FALSE | Z864: 1
A865: 3779 | B865: banks_global_financials_and_ratios_usd_interim | C865: audit_status | D865: Audit_status | E865: =VLOOKUP(SUBSTITUTE(B865,"_usd_","_eur_")&" - "&D865,OrbisGeneric_mapping!C:F,3,0) -> AUDIT_STATUS | F865: =VLOOKUP(E865,Collibra!D:F,3,0) -> Audit status | G865: =VLOOKUP(E865,Collibra!D:F,2,0) -> The audit status indicates the status of a statement with regard to its auditing. A financial accounts audit status could fall into qualified, unqualified, unaudited, adverse opinion, no opinion, qualification not available. This information is almost only available for publicy listed companies. | J865: STRING | N865: FALSE | P865: 2025-08-29T13:46:54.659Z | Q865: 2025-08-29T13:46:54.663Z | R865: FALSE | Z865: 1
A866: 3723 | B866: banks_global_financials_and_ratios_usd_interim | C866: bvd_id_number | D866: BvD_ID_number | E866: =VLOOKUP(SUBSTITUTE(B866,"_usd_","_eur_")&" - "&D866,OrbisGeneric_mapping!C:F,3,0) -> BVD_ID_NUMBER | F866: =VLOOKUP(E866,Collibra!D:F,3,0) -> BvD ID number | G866: =VLOOKUP(E866,Collibra!D:F,2,0) -> <p class="MsoNormal"><span style="font-size: 9.0pt;font-family: Arial , sans-serif;color: rgb(11,33,44);">The BvD ID number is a company identifier that uniquely identifies each company included in at least one Bureau van Dijk product. The first two characters correspond to the ISO country code (according the ISO 3166-1 alpha-2 standard) where the company is incorporated. The rest of a BvD ID number may vary and be based on a national ID, an information provider's ID, an own internal ID.</span> As a result, BvD ID numbers may be subject to change due to changes in national IDs or an information provider's ID.</p> | J866: STRING | N866: FALSE | P866: 2025-08-29T13:46:54.659Z | Q866: 2025-08-29T13:46:54.663Z | R866: FALSE | Z866: 1
A867: 4363 | B867: banks_global_financials_and_ratios_usd_interim | C867: cap_funds_dep_st_funding_ | D867: Cap_Funds_Dep_ST_Funding_ | E867: =VLOOKUP(SUBSTITUTE(B867,"_usd_","_eur_")&" - "&D867,OrbisGeneric_mapping!C:F,3,0) -> 195160 | F867: =VLOOKUP(E867,Collibra!D:F,3,0) -> #N/A | G867: =VLOOKUP(E867,Collibra!D:F,2,0) -> #N/A | J867: STRING | N867: FALSE | P867: 2025-08-29T13:46:54.659Z | Q867: 2025-08-29T13:46:54.663Z | R867: FALSE | Z867: 1
A868: 4371 | B868: banks_global_financials_and_ratios_usd_interim | C868: cap_funds_liabilities_ | D868: Cap_Funds_Liabilities_ | E868: =VLOOKUP(SUBSTITUTE(B868,"_usd_","_eur_")&" - "&D868,OrbisGeneric_mapping!C:F,3,0) -> 195170 | F868: =VLOOKUP(E868,Collibra!D:F,3,0) -> #N/A | G868: =VLOOKUP(E868,Collibra!D:F,2,0) -> #N/A | J868: STRING | N868: FALSE | P868: 2025-08-29T13:46:54.659Z | Q868: 2025-08-29T13:46:54.663Z | R868: FALSE | Z868: 1
A869: 4355 | B869: banks_global_financials_and_ratios_usd_interim | C869: cap_funds_net_loans_ | D869: Cap_Funds_Net_Loans_ | E869: =VLOOKUP(SUBSTITUTE(B869,"_usd_","_eur_")&" - "&D869,OrbisGeneric_mapping!C:F,3,0) -> 195150 | F869: =VLOOKUP(E869,Collibra!D:F,3,0) -> #N/A | G869: =VLOOKUP(E869,Collibra!D:F,2,0) -> #N/A | J869: STRING | N869: FALSE | P869: 2025-08-29T13:46:54.659Z | Q869: 2025-08-29T13:46:54.663Z | R869: FALSE | Z869: 1
A870: 4347 | B870: banks_global_financials_and_ratios_usd_interim | C870: cap_funds_total_assets_ | D870: Cap_Funds_Total_assets_ | E870: =VLOOKUP(SUBSTITUTE(B870,"_usd_","_eur_")&" - "&D870,OrbisGeneric_mapping!C:F,3,0) -> 195140 | F870: =VLOOKUP(E870,Collibra!D:F,3,0) -> #N/A | G870: =VLOOKUP(E870,Collibra!D:F,2,0) -> #N/A | J870: STRING | N870: FALSE | P870: 2025-08-29T13:46:54.659Z | Q870: 2025-08-29T13:46:54.663Z | R870: FALSE | Z870: 1
A871: 3739 | B871: banks_global_financials_and_ratios_usd_interim | C871: closing_date | D871: Closing_date | E871: =VLOOKUP(SUBSTITUTE(B871,"_usd_","_eur_")&" - "&D871,OrbisGeneric_mapping!C:F,3,0) -> CLOSING_DATE | F871: =VLOOKUP(E871,Collibra!D:F,3,0) -> Closing date | G871: =VLOOKUP(E871,Collibra!D:F,2,0) -> Closing date provides the financial accounts year or interim ending date (Default: Latest available year) | J871: STRING | N871: FALSE | P871: 2025-08-29T13:46:54.659Z | Q871: 2025-08-29T13:46:54.663Z | R871: FALSE | Z871: 1
A872: 3763 | B872: banks_global_financials_and_ratios_usd_interim | C872: closing_date_day | D872: Closing_date_day | E872: =VLOOKUP(SUBSTITUTE(B872,"_usd_","_eur_")&" - "&D872,OrbisGeneric_mapping!C:F,3,0) -> #N/A | F872: =VLOOKUP(E872,Collibra!D:F,3,0) -> #N/A | G872: =VLOOKUP(E872,Collibra!D:F,2,0) -> #N/A | J872: STRING | N872: FALSE | P872: 2025-08-29T13:46:54.659Z | Q872: 2025-08-29T13:46:54.663Z | R872: FALSE | Z872: 1
A873: 3755 | B873: banks_global_financials_and_ratios_usd_interim | C873: closing_date_month | D873: Closing_date_month | E873: =VLOOKUP(SUBSTITUTE(B873,"_usd_","_eur_")&" - "&D873,OrbisGeneric_mapping!C:F,3,0) -> #N/A | F873: =VLOOKUP(E873,Collibra!D:F,3,0) -> #N/A | G873: =VLOOKUP(E873,Collibra!D:F,2,0) -> #N/A | J873: STRING | N873: FALSE | P873: 2025-08-29T13:46:54.659Z | Q873: 2025-08-29T13:46:54.663Z | R873: FALSE | Z873: 1
A874: 3747 | B874: banks_global_financials_and_ratios_usd_interim | C874: closing_date_year | D874: Closing_date_year | E874: =VLOOKUP(SUBSTITUTE(B874,"_usd_","_eur_")&" - "&D874,OrbisGeneric_mapping!C:F,3,0) -> #N/A | F874: =VLOOKUP(E874,Collibra!D:F,3,0) -> #N/A | G874: =VLOOKUP(E874,Collibra!D:F,2,0) -> #N/A | J874: STRING | N874: FALSE | P874: 2025-08-29T13:46:54.659Z | Q874: 2025-08-29T13:46:54.663Z | R874: FALSE | Z874: 1
A875: 3731 | B875: banks_global_financials_and_ratios_usd_interim | C875: consolidation_code | D875: Consolidation_code | E875: =VLOOKUP(SUBSTITUTE(B875,"_usd_","_eur_")&" - "&D875,OrbisGeneric_mapping!C:F,3,0) -> CONSOLIDATION_CODE | F875: =VLOOKUP(E875,Collibra!D:F,3,0) -> Consolidation code | G875: =VLOOKUP(E875,Collibra!D:F,2,0) -> <p>Consolidation code defines whether a financial statement is Consolidated or Unconsolidated. Based on the number of financials statements published in a report, a numeric suffix is added (C1, C2, U1 and U2) to distinguish the reports available between various entities. Suffix 1 refers the entity publishes consolidated/unconsolidated only while suffix 2 represents the entity publishes both Consolidated and Unconsolidated in the same report. Similarly, to distinguish availability of additional consolidated or unconsolidated statement suffix * is added (C* and U*). Additional financial statements appears if the entity has different accounting standard or more than one source.</p> <p>Companies with limited financial data are those with a consolidation code of LF (limited financials). The information available for such companies is often based on rounded figures - or class level - officially available (sometimes also collected from other directories or web sites). In most cases only “Number of employees” and “Operating Revenue” are available. There are several countries where detailed financials are not available for some companies. In such cases, LF are quite often made of median value of revenue range (or estimate), median value of employee range (or estimate) and current capital. Figures are reported for the current year (when recently collected and reflecting latest situation) such as YYYY. Figures might change during the course of Year YYYY until 31/12/YYYY when they are fixed and new figures are reported for Year YYYY+1.</p> | J875: STRING | N875: FALSE | P875: 2025-08-29T13:46:54.659Z | Q875: 2025-08-29T13:46:54.663Z | R875: FALSE | Z875: 1
... A982: 4283 | B982: banks_global_financials_and_ratios_usd_interim | C982: unreserved_impaired_loans_equity_ | D982: Unreserved_impaired_loans_Equity_ | E982: =VLOOKUP(SUBSTITUTE(B982,"_usd_","_eur_")&" - "&D982,OrbisGeneric_mapping!C:F,3,0) -> 195070 | F982: =VLOOKUP(E982,Collibra!D:F,3,0) -> #N/A | G982: =VLOOKUP(E982,Collibra!D:F,2,0) -> #N/A | J982: STRING | N982: FALSE | P982: 2025-08-29T13:46:54.659Z | Q982: 2025-08-29T13:46:54.663Z | R982: FALSE | Z982: 1
A983: 3941 | B983: basic_shareholder_info | C983: bvd_id_number | D983: BvD_ID_number | E983: =VLOOKUP(B983&" - "&D983,OrbisGeneric_mapping!C:F,3,0) -> BVD_ID_NUMBER | F983: =VLOOKUP(E983,Collibra!D:F,3,0) -> BvD ID number | G983: =VLOOKUP(E983,Collibra!D:F,2,0) -> <p class="MsoNormal"><span style="font-size: 9.0pt;font-family: Arial , sans-serif;color: rgb(11,33,44);">The BvD ID number is a company identifier that uniquely identifies each company included in at least one Bureau van Dijk product. The first two characters correspond to the ISO country code (according the ISO 3166-1 alpha-2 standard) where the company is incorporated. The rest of a BvD ID number may vary and be based on a national ID, an information provider's ID, an own internal ID.</span> As a result, BvD ID numbers may be subject to change due to changes in national IDs or an information provider's ID.</p> | J983: STRING | N983: FALSE | P983: 2025-08-29T13:46:54.659Z | Q983: 2025-08-29T13:46:54.663Z | R983: FALSE | Z983: 1
A984: 3949 | B984: basic_shareholder_info | C984: bvd_independence_indicator | D984: BvD_Independence_Indicator | E984: =VLOOKUP(B984&" - "&D984,OrbisGeneric_mapping!C:F,3,0) -> INDEPENDENCE_INDICATOR | F984: =VLOOKUP(E984,Collibra!D:F,3,0) -> BvD Independence Indicator | G984: =VLOOKUP(E984,Collibra!D:F,2,0) -> <p class="MsoNormal">This field provides the Independence Indicator of the concerned entity. </p> <p class="MsoNormal">To assist users in identifying independent companies on our products, Bureau van Dijk has created an Independence Indicator to characterise the degree of independence of a company with regard to its shareholders. This BvD Independence Indicator is assigned to each company according to the logic defined below.</p> <p class="MsoNormal">First note that the categories of shareholders collectively labelled by the sources are disregarded in the considerations below (since they are considered as unable to exert a controlling power over a company). They include:</p> <ul> <li class="MsoNormal"><span style="text-indent: -18.0pt;">Public (used only for quoted companies)</span></li> <li class="MsoNormal">Unnamed private shareholders, aggregated (more than one unnamed individual or family, labelled as “Private shareholders”, “Individual investors”, “Other individuals”, and so on.)</li> <li class="MsoNormal">Other unnamed shareholders, aggregated (more than one unnamed shareholder containing a mixture of companies or of companies and individuals or families).</li> </ul> <p class="MsoNormal">The BvD Independence Indicators are noted as A, B, C, D and U, with confidence levels.</p> <p class="MsoNormal"><span style="text-decoration: underline;">Indicator A: Independent company</span></p> <p class="MsoNormal">Attached to any company with known recorded shareholders (excluding the three “collective” types indicated above) none of which having more than 25% of direct or total ownership.</p> <p class="MsoNormal">We also give a confidence level:</p> <ul> <li class="MsoNormal"><span style="text-indent: -18.0pt;">High(A+): Companies with six or more identified shareholders (of any type) whose ownership percentage is known</span></li> <li class="MsoNormal">Medium(A): As above, but includes companies with four or five identified shareholders</li> <li class="MsoNormal">Low (A-): As above, but includes companies with one to three identified shareholders</li> </ul> <p class="MsoNormal">The logic behind these confidence levels is that the probability of having missed an ownership percentage over 25% is the lowest when the greatest number of shareholders is known, so that the company's degree of independence is more certain.</p> <p class="MsoNormal">The confidence level ‘High’ (A+) is also attributed to A companies in which the sum of direct ownership links (all categories of shareholders included) is over 75%. Which means that those companies cannot have an unknown shareholder with 25% or more and can thus not be identified with an Independence Indicator other than A.</p> <p class="MsoNormal">Please note that Bureau van Dijk also gives an A- notation to a company that is mentioned by a source (Annual Report, Private Communication or Information Provider) as being the Ultimate Owner of another company, even when its shareholders are not mentioned.</p> <p class="MsoNormal">As it can been seen from the above definitions, the qualifications “+” or “-” do not refer to a higher or a lower degree of independence but to the degree of reliability of the Indicator that is attributed.</p> <p class="MsoNormal"><strong>Particular case:</strong></p> <p class="MsoNormal">A company may report having at least one recorded shareholder with an interest in the company over a certain percentage (&gt;X%).</p> <p class="MsoNormal">If this percentage is under 25%, as we do not know the exact percentage of ownership, it is difficult to determine the level of independence. For such companies, specific rules are applied:</p> <ul> <li class="MsoNormal">If only one shareholder is reported to own over X% (and X≤25), then it is clear that we cannot determine if the shareholder has control or not so we assign the independence indicator U.</li> <li class="MsoNormal">If several shareholders are known, no one with more than 25% but with perhaps several reported to own over X% (X≤25), it is still difficult to determine the level of control and we also assign the independence indicator U.</li> <li class="MsoNormal">In only one case, we will still assign A+: when the remaining unknown direct percentage added to the percentage of any shareholder reported to own over X% is lower to 25%. This means no one of those shareholders, even if they would own the remaining unknown percentage, will have more than 25% and change the independence indicator to B.</li> </ul> <p class="MsoNormal">In Bureau van Dijk terminology “A" companies are called “Independent companies”.</p> <p class="MsoNormal"><span style="text-decoration: underline;">Indicator B: No majority ownership</span></p> <p class="MsoNormal">Attached to any company with a known recorded shareholder (excluding the three “collective” types mentioned above) none of which with an ownership percentage (direct, total or calculated total) over 50%, but having one or more shareholders with an ownership percentage above 25%.</p> <p class="MsoNormal">The confidence level ‘High’ (B+), Medium (B) or Low (B-) further qualification as B+, B and B- is assigned according to the same criteria relating to the number of recorded shareholders as for indicator A.</p> <p class="MsoNormal">The confidence level ‘High’ (B+) is also attributed to B companies in which the summation of direct ownership percentages (all categories of shareholders included) is 50.01% and higher. Indeed, this means that the company surely does not qualify under Independent Indicator C (since it cannot have an unknown shareholder with 50.01% or higher).</p> <p class="MsoNormal"><span style="text-decoration: underline;">Indicator C: Indirect majority ownership</span></p> <p class="MsoNormal">Attached to any company with a recorded shareholder (excluding the three “collective” types mentioned above) with a total or a calculated total ownership over 50%.</p> <p class="MsoNormal">The confidence level ‘High’ (C+) is attributed to C companies in which the summation of direct ownership percentage (all categories of shareholders included) is 50.01% or higher. Indeed, this means that the company surely does not qualify under Independent Indicator D (since it cannot have an unknown direct shareholder with 50.01% or higher).</p> <p class="MsoNormal">The C indicator is also given to a company when a source indicates that the company has an Ultimate Owner, even though its percentage of ownership is unknown.</p> <p class="MsoNormal"><span style="text-decoration: underline;">Indicator D: Direct majority ownership</span></p> <p class="MsoNormal">This is allocated to any company with a recorded shareholder (excluding the three “collective” types mentioned above) with a direct ownership of over 50%. Branches, foreign companies and marine vessels are also being attributed an indicator ‘D’.</p> <p class="MsoNormal"><span style="text-decoration: underline;">Indicator U: Unknown independence status</span></p> <p class="MsoNormal">This is allocated to companies that don’t fall into the categories A, B, C or D; indicating an unknown degree of independence.</p> <p class="MsoNormal">Indicator - :</p> <p class="MsoNormal">Attached to any entity which is considered to be “independent” by nature (states and individuals) or to inactive companies.</p> | J984: STRING | N984: FALSE | P984: 2025-08-29T13:46:54.659Z | Q984: 2025-08-29T13:46:54.663Z | R984: FALSE | Z984: 1
A985: 4389 | B985: basic_shareholder_info | C985: duo_also_a_manager | D985: DUO_Also_a_manager | E985: =VLOOKUP(B985&" - "&D985,OrbisGeneric_mapping!C:F,3,0) -> DUO_ALSO_MANAGER_INDICATOR | F985: =VLOOKUP(E985,Collibra!D:F,3,0) -> #N/A | G985: =VLOOKUP(E985,Collibra!D:F,2,0) -> #N/A | J985: STRING | N985: FALSE | P985: 2025-08-29T13:46:54.659Z | Q985: 2025-08-29T13:46:54.663Z | R985: FALSE | Z985: 1
A986: 4293 | B986: basic_shareholder_info | C986: duo_bvd_id_number | D986: DUO_BvD_ID_number | E986: =VLOOKUP(B986&" - "&D986,OrbisGeneric_mapping!C:F,3,0) -> DUO_BVD_ID_NUMBER | F986: =VLOOKUP(E986,Collibra!D:F,3,0) -> 0 | G986: =VLOOKUP(E986,Collibra!D:F,2,0) -> Gives the BvD ID of the Domestic Ultimate Owner. It is never empty | J986: STRING | N986: FALSE | P986: 2025-08-29T13:46:54.659Z | Q986: 2025-08-29T13:46:54.663Z | R986: FALSE | Z986: 1
A987: 4309 | B987: basic_shareholder_info | C987: duo_city | D987: DUO_City | E987: =VLOOKUP(B987&" - "&D987,OrbisGeneric_mapping!C:F,3,0) -> DUO_CITY | F987: =VLOOKUP(E987,Collibra!D:F,3,0) -> 0 | G987: =VLOOKUP(E987,Collibra!D:F,2,0) -> Gives the city where the Domestic Ultimate Owner is located. | J987: STRING | N987: FALSE | P987: 2025-08-29T13:46:54.659Z | Q987: 2025-08-29T13:46:54.663Z | R987: FALSE | Z987: 1
A988: 4301 | B988: basic_shareholder_info | C988: duo_country_iso_code | D988: DUO_Country_ISO_code | E988: =VLOOKUP(B988&" - "&D988,OrbisGeneric_mapping!C:F,3,0) -> DUO_COUNTRY_ISO_CODE | F988: =VLOOKUP(E988,Collibra!D:F,3,0) -> Domestic Ultimate Owner - Country ISO code | G988: =VLOOKUP(E988,Collibra!D:F,2,0) -> 2 digit iso country code. If not known, the code 'YY' is used. | J988: STRING | N988: FALSE | P988: 2025-08-29T13:46:54.659Z | Q988: 2025-08-29T13:46:54.663Z | R988: FALSE | Z988: 1
A989: 4333 | B989: basic_shareholder_info | C989: duo_direct_ | D989: DUO_Direct_ | E989: =VLOOKUP(B989&" - "&D989,OrbisGeneric_mapping!C:F,3,0) -> DUO_DIRECT_PCT | F989: =VLOOKUP(E989,Collibra!D:F,3,0) -> DUO - Direct % | G989: =VLOOKUP(E989,Collibra!D:F,2,0) -> This field is the direct percentage owned by the shareholder in the company just below in the BO path. | J989: STRING | N989: FALSE | P989: 2025-08-29T13:46:54.659Z | Q989: 2025-08-29T13:46:54.663Z | R989: FALSE | Z989: 1
A990: 4277 | B990: basic_shareholder_info | C990: duo_first_name | D990: DUO_First_name | E990: =VLOOKUP(B990&" - "&D990,OrbisGeneric_mapping!C:F,3,0) -> DUO_FIRST_NAME | F990: =VLOOKUP(E990,Collibra!D:F,3,0) -> DUO - First name | G990: =VLOOKUP(E990,Collibra!D:F,2,0) -> This field provides the first name of the Domestic Ultimate Owner. This has been extracted from the full name when possible. | J990: STRING | N990: FALSE | P990: 2025-08-29T13:46:54.659Z | Q990: 2025-08-29T13:46:54.663Z | R990: FALSE | Z990: 1
A991: 4357 | B991: basic_shareholder_info | C991: duo_information_date | D991: DUO_Information_date | E991: =VLOOKUP(B991&" - "&D991,OrbisGeneric_mapping!C:F,3,0) -> DUO_INFORMATION_DATE | F991: =VLOOKUP(E991,Collibra!D:F,3,0) -> DUO - Information date | G991: =VLOOKUP(E991,Collibra!D:F,2,0) -> This field is a date with format MM/YYYY that represents the validity date of information (i.e. the date of the annual report from which the information comes from; or the date indicated on the website; or when there is no date, the date of the collection of the information). This is not the date that the entity was added into our product. If a source is not able to provide us such a date, Bureau van Dijk assesses the best date reflecting the information confirmation. The date of information might be updated although the shareholder or the percentage remains the same, as long as we receive a confirmation for this information. | J991: STRING | N991: FALSE | P991: 2025-08-29T13:46:54.659Z | Q991: 2025-08-29T13:46:54.663Z | R991: FALSE | Z991: 1
A992: 4381 | B992: basic_shareholder_info | C992: duo_information_date_day | D992: DUO_Information_date_day | E992: =VLOOKUP(B992&" - "&D992,OrbisGeneric_mapping!C:F,3,0) -> #N/A | F992: =VLOOKUP(E992,Collibra!D:F,3,0) -> #N/A | G992: =VLOOKUP(E992,Collibra!D:F,2,0) -> #N/A | J992: STRING | N992: FALSE | P992: 2025-08-29T13:46:54.659Z | Q992: 2025-08-29T13:46:54.663Z | R992: FALSE | Z992: 1
A993: 4373 | B993: basic_shareholder_info | C993: duo_information_date_month | D993: DUO_Information_date_month | E993: =VLOOKUP(B993&" - "&D993,OrbisGeneric_mapping!C:F,3,0) -> #N/A | F993: =VLOOKUP(E993,Collibra!D:F,3,0) -> #N/A | G993: =VLOOKUP(E993,Collibra!D:F,2,0) -> #N/A | J993: STRING | N993: FALSE | P993: 2025-08-29T13:46:54.659Z | Q993: 2025-08-29T13:46:54.663Z | R993: FALSE | Z993: 1
A994: 4365 | B994: basic_shareholder_info | C994: duo_information_date_year | D994: DUO_Information_date_year | E994: =VLOOKUP(B994&" - "&D994,OrbisGeneric_mapping!C:F,3,0) -> #N/A | F994: =VLOOKUP(E994,Collibra!D:F,3,0) -> #N/A | G994: =VLOOKUP(E994,Collibra!D:F,2,0) -> #N/A | J994: STRING | N994: FALSE | P994: 2025-08-29T13:46:54.659Z | Q994: 2025-08-29T13:46:54.663Z | R994: FALSE | Z994: 1
... A1124: 4194 | B1124: beneficial_owners_10_10_with_boi | C1124: row_num | D1124: row_num | E1124: =VLOOKUP(B1124&" - "&D1124,OrbisGeneric_mapping!C:F,3,0) -> #N/A | F1124: =VLOOKUP(E1124,Collibra!D:F,3,0) -> #N/A | G1124: =VLOOKUP(E1124,Collibra!D:F,2,0) -> #N/A | J1124: BIGINT | N1124: FALSE | P1124: 2025-08-29T13:46:54.659Z | Q1124: 2025-08-29T13:46:54.663Z | R1124: FALSE | Z1124: 1
A1125: 5068 | B1125: beneficial_owners_10_50_with_boi | C1125: beneficial_owner_address | D1125: Beneficial_owner_address | E1125: =VLOOKUP(SUBSTITUTE(B1125,"_10_50_","_10_10_")&" - "&D1125,OrbisGeneric_mapping!C:F,3,0) -> BO_ADDRESS | F1125: =VLOOKUP(E1125,Collibra!D:F,3,0) -> Beneficial owner address | G1125: =VLOOKUP(E1125,Collibra!D:F,2,0) -> Gives the address of the Beneficial owner. This field includes the street, the number of the building where the entity is located and the number of the floor of the building if available. | J1125: STRING | N1125: FALSE | P1125: 2025-08-29T13:46:54.659Z | Q1125: 2025-08-29T13:46:54.663Z | R1125: FALSE | Z1125: 1
A1126: 21 | B1126: beneficial_owners_10_50_with_boi | C1126: beneficial_owner_also_a_manager | D1126: Beneficial_owner_Also_a_manager | E1126: =VLOOKUP(SUBSTITUTE(B1126,"_10_50_","_10_10_")&" - "&D1126,OrbisGeneric_mapping!C:F,3,0) -> BO_CURRENT_PREVIOUS_MANAGER | F1126: =VLOOKUP(E1126,Collibra!D:F,3,0) -> Beneficial owner - Also a manager | G1126: =VLOOKUP(E1126,Collibra!D:F,2,0) -> Indicating if the Beneficial owner is also a manager. Can take 3 values : Not a manager, current manager, previous manager | J1126: STRING | N1126: FALSE | P1126: 2025-08-29T13:46:54.659Z | Q1126: 2025-08-29T13:46:54.663Z | R1126: FALSE | Z1126: 1
A1127: 4980 | B1127: beneficial_owners_10_50_with_boi | C1127: beneficial_owner_bvd_id_number | D1127: Beneficial_owner_BvD_ID_number | E1127: =VLOOKUP(SUBSTITUTE(B1127,"_10_50_","_10_10_")&" - "&D1127,OrbisGeneric_mapping!C:F,3,0) -> BO_BVD_ID_NUMBER | F1127: =VLOOKUP(E1127,Collibra!D:F,3,0) -> Beneficial owner BvD ID number | G1127: =VLOOKUP(E1127,Collibra!D:F,2,0) -> Gives the BvD ID of the beneficial owners. It is never empty | J1127: STRING | N1127: FALSE | P1127: 2025-08-29T13:46:54.659Z | Q1127: 2025-08-29T13:46:54.663Z | R1127: FALSE | Z1127: 1
A1128: 5076 | B1128: beneficial_owners_10_50_with_boi | C1128: beneficial_owner_city | D1128: Beneficial_owner_city | E1128: =VLOOKUP(SUBSTITUTE(B1128,"_10_50_","_10_10_")&" - "&D1128,OrbisGeneric_mapping!C:F,3,0) -> BO_CITY | F1128: =VLOOKUP(E1128,Collibra!D:F,3,0) -> Beneficial owner city | G1128: =VLOOKUP(E1128,Collibra!D:F,2,0) -> Gives the city where the Beneficial owner is located. | J1128: STRING | N1128: FALSE | P1128: 2025-08-29T13:46:54.659Z | Q1128: 2025-08-29T13:46:54.663Z | R1128: FALSE | Z1128: 1
A1129: 5 | B1129: beneficial_owners_10_50_with_boi | C1129: beneficial_owner_country | D1129: Beneficial_owner_country | E1129: =VLOOKUP(SUBSTITUTE(B1129,"_10_50_","_10_10_")&" - "&D1129,OrbisGeneric_mapping!C:F,3,0) -> BO_COUNTRY_ISO_CODE | F1129: =VLOOKUP(E1129,Collibra!D:F,3,0) -> Beneficial owner country | G1129: =VLOOKUP(E1129,Collibra!D:F,2,0) -> 2 digit iso country code. If not known, the code 'YY' is used. | J1129: STRING | N1129: FALSE | P1129: 2025-08-29T13:46:54.659Z | Q1129: 2025-08-29T13:46:54.663Z | R1129: FALSE | Z1129: 1
A1130: 5036 | B1130: beneficial_owners_10_50_with_boi | C1130: beneficial_owner_date_of_birth_rarely_available_due_to_legal_restrictions_ | D1130: Beneficial_owner_date_of_birth_rarely_available_due_to_legal_restrictions_ | E1130: =VLOOKUP(SUBSTITUTE(B1130,"_10_50_","_10_10_")&" - "&D1130,OrbisGeneric_mapping!C:F,3,0) -> BO_BIRTHDATE | F1130: =VLOOKUP(E1130,Collibra!D:F,3,0) -> Beneficial owner date of birth (rarely available due to legal restrictions) | G1130: =VLOOKUP(E1130,Collibra!D:F,2,0) -> Gives the brithdate of the beneficial owner if available, can be complete (DD/MM/YYYY) or not (MM/YYYY or YYYY) - date format depends on the product settings | J1130: STRING | N1130: FALSE | P1130: 2025-08-29T13:46:54.659Z | Q1130: 2025-08-29T13:46:54.663Z | R1130: FALSE | Z1130: 1
A1131: 5060 | B1131: beneficial_owners_10_50_with_boi | C1131: beneficial_owner_date_of_birth_rarely_available_due_to_legal_restrictions__day | D1131: Beneficial_owner_date_of_birth_rarely_available_due_to_legal_restrictions__day | E1131: =VLOOKUP(SUBSTITUTE(B1131,"_10_50_","_10_10_")&" - "&D1131,OrbisGeneric_mapping!C:F,3,0) -> #N/A | F1131: =VLOOKUP(E1131,Collibra!D:F,3,0) -> #N/A | G1131: =VLOOKUP(E1131,Collibra!D:F,2,0) -> #N/A | J1131: STRING | N1131: FALSE | P1131: 2025-08-29T13:46:54.659Z | Q1131: 2025-08-29T13:46:54.663Z | R1131: FALSE | Z1131: 1
A1132: 5052 | B1132: beneficial_owners_10_50_with_boi | C1132: beneficial_owner_date_of_birth_rarely_available_due_to_legal_restrictions__month | D1132: Beneficial_owner_date_of_birth_rarely_available_due_to_legal_restrictions__month | E1132: =VLOOKUP(SUBSTITUTE(B1132,"_10_50_","_10_10_")&" - "&D1132,OrbisGeneric_mapping!C:F,3,0) -> #N/A | F1132: =VLOOKUP(E1132,Collibra!D:F,3,0) -> #N/A | G1132: =VLOOKUP(E1132,Collibra!D:F,2,0) -> #N/A | J1132: STRING | N1132: FALSE | P1132: 2025-08-29T13:46:54.659Z | Q1132: 2025-08-29T13:46:54.663Z | R1132: FALSE | Z1132: 1
...

Sheet OrbisGeneric_mapping
A1: Table name (raw) | B1: Table name | C1: Helper column | D1: Field name | E1: Bvd Codes | F1: cleansed field name
A2: Modelled_employee_sales_assets.txt | B2: =LEFT(A2,FIND(".txt",A2)-1) -> Modelled_employee_sales_assets | C2: =B2&" - "&F2 -> Modelled_employee_sales_assets - BvD_ID_number | D2: BvD ID number | E2: BVD_ID_NUMBER | F2: BvD_ID_number
A3: Modelled_employee_sales_assets.txt | B3: =LEFT(A3,FIND(".txt",A3)-1) -> Modelled_employee_sales_assets | C3: =B3&" - "&F3 -> Modelled_employee_sales_assets - Orbis_ID_number | D3: Orbis ID number | E3: ORBISID | F3: Orbis_ID_number
A4: Modelled_employee_sales_assets.txt | B4: =LEFT(A4,FIND(".txt",A4)-1) -> Modelled_employee_sales_assets | C4: =B4&" - "&F4 -> Modelled_employee_sales_assets - Model_data_Subject_corporate_group_linkage_description | D4: Model data - Subject corporate group linkage description | E4: SUBJECT_CORPORATE_GROUP_LINKAGE_DESCRIPTION | F4: Model_data_Subject_corporate_group_linkage_description
A5: Modelled_employee_sales_assets.txt | B5: =LEFT(A5,FIND(".txt",A5)-1) -> Modelled_employee_sales_assets | C5: =B5&" - "&F5 -> Modelled_employee_sales_assets - Model_data_Global_parent_bvdid | D5: Model data - Global parent bvdid | E5: MODEL_DATA_GLOBAL_PARENT_BVDID | F5: Model_data_Global_parent_bvdid
A6: Modelled_employee_sales_assets.txt | B6: =LEFT(A6,FIND(".txt",A6)-1) -> Modelled_employee_sales_assets | C6: =B6&" - "&F6 -> Modelled_employee_sales_assets - Model_data_Global_parent_operating_revenue_USD | D6: Model data - Global parent operating revenue USD | E6: MODEL_DATA_GLOBAL_PARENT_OPERATING_REVENUE | F6: Model_data_Global_parent_operating_revenue_USD
A7: Modelled_employee_sales_assets.txt | B7: =LEFT(A7,FIND(".txt",A7)-1) -> Modelled_employee_sales_assets | C7: =B7&" - "&F7 -> Modelled_employee_sales_assets - Model_data_Global_parent_operating_revenue_accuracy_indicator | D7: Model data - Global parent operating revenue accuracy indicator | E7: MODEL_DATA_GLOBAL_PARENT_OPERATING_REVENUE_ACCURACY_INDICATOR | F7: Model_data_Global_parent_operating_revenue_accuracy_indicator
A8: Modelled_employee_sales_assets.txt | B8: =LEFT(A8,FIND(".txt",A8)-1) -> Modelled_employee_sales_assets | C8: =B8&" - "&F8 -> Modelled_employee_sales_assets - Model_data_Global_parent_number_of_employees | D8: Model data - Global parent number of employees | E8: MODEL_DATA_GLOBAL_PARENT_NUMBER_OF_EMPLOYEES | F8: Model_data_Global_parent_number_of_employees
A9: Modelled_employee_sales_assets.txt | B9: =LEFT(A9,FIND(".txt",A9)-1) -> Modelled_employee_sales_assets | C9: =B9&" - "&F9 -> Modelled_employee_sales_assets - Model_data_Global_parent_number_of_employees_accuracy_indicator | D9: Model data - Global parent number of employees accuracy indicator | E9: MODEL_DATA_GLOBAL_PARENT_NUMBER_OF_EMPLOYEES_ACCURACY_INDICATOR | F9: Model_data_Global_parent_number_of_employees_accuracy_indicator
A10: Modelled_employee_sales_assets.txt | B10: =LEFT(A10,FIND(".txt",A10)-1) -> Modelled_employee_sales_assets | C10: =B10&" - "&F10 -> Modelled_employee_sales_assets - Model_data_Global_parent_total_assets | D10: Model data - Global parent total assets | E10: MODEL_DATA_GLOBAL_PARENT_TOTAL_ASSETS | F10: Model_data_Global_parent_total_assets
A11: Modelled_employee_sales_assets.txt | B11: =LEFT(A11,FIND(".txt",A11)-1) -> Modelled_employee_sales_assets | C11: =B11&" - "&F11 -> Modelled_employee_sales_assets - Model_data_Global_parent_total_assets_accuracy_indicator | D11: Model data - Global parent total assets accuracy indicator | E11: MODEL_DATA_GLOBAL_PARENT_TOTAL_ASSETS_ACCURACY_INDICATOR | F11: Model_data_Global_parent_total_assets_accuracy_indicator
A12: Modelled_employee_sales_assets.txt | B12: =LEFT(A12,FIND(".txt",A12)-1) -> Modelled_employee_sales_assets | C12: =B12&" - "&F12 -> Modelled_employee_sales_assets - Model_data_Calculation_date | D12: Model data - Calculation date | E12: MODEL_DATA_CALCULATION_DATE | F12: Model_data_Calculation_date
A13: Cyber_risk_rating_by_BitSight.txt | B13: =LEFT(A13,FIND(".txt",A13)-1) -> Cyber_risk_rating_by_BitSight | C13: =B13&" - "&F13 -> Cyber_risk_rating_by_BitSight - BvD_ID_number | D13: BvD ID number | E13: BVD_ID_NUMBER | F13: BvD_ID_number
... A336: Contact_info.txt (one line per company) | B336: =LEFT(A336,FIND(".txt",A336)-1) -> Contact_info | C336: =B336&" - "&F336 -> Contact_info - LONGITUDE | D336: LONGITUDE | E336: LONGITUDE | F336: LONGITUDE
A337: Contact_info.txt (one line per company) | B337: =LEFT(A337,FIND(".txt",A337)-1) -> Contact_info | C337: =B337&" - "&F337 -> Contact_info - Remarks_ | D337: Remarks: | F337: Remarks_
A338: Contact_info.txt (one line per company) | B338: =LEFT(A338,FIND(".txt",A338)-1) -> Contact_info | C338: =B338&" - "&F338 -> Contact_info - Priority_given_to_info_from_local_registry_filings | D338: Priority given to info from local registry filings | F338: Priority_given_to_info_from_local_registry_filings
A339: Contact_info.txt (one line per company) | B339: =LEFT(A339,FIND(".txt",A339)-1) -> Contact_info | C339: =B339&" - "&F339 -> Contact_info - Region_in_country_and_type_of_region_in_country_have_multiple_values_separated_by_a_pipe | D339: Region in country and type of region in country have multiple values separated by a pipe | F339: Region_in_country_and_type_of_region_in_country_have_multiple_values_separated_by_a_pipe
A340: All_addresses.txt (several lines per company) | B340: =LEFT(A340,FIND(".txt",A340)-1) -> All_addresses | C340: =B340&" - "&F340 -> All_addresses - BvD_ID_number | D340: BvD ID number | E340: BVD_ID_NUMBER | F340: BvD_ID_number
A341: All_addresses.txt (several lines per company) | B341: =LEFT(A341,FIND(".txt",A341)-1) -> All_addresses | C341: =B341&" - "&F341 -> All_addresses - Street_no_building_etc_line_1 | D341: Street, no., building etc, line 1 | E341: ADDRESS_LINE1_ADDITIONAL_INTERNATIONAL | F341: Street_no_building_etc_line_1
A342: All_addresses.txt (several lines per company) | B342: =LEFT(A342,FIND(".txt",A342)-1) -> All_addresses | C342: =B342&" - "&F342 -> All_addresses - Street_no_building_etc_line_1_native_ | D342: Street, no., building etc, line 1 (native) | E342: ADDRESS_LINE1_ADDITIONAL_LOCAL | F342: Street_no_building_etc_line_1_native_
A343: All_addresses.txt (several lines per company) | B343: =LEFT(A343,FIND(".txt",A343)-1) -> All_addresses | C343: =B343&" - "&F343 -> All_addresses - Street_no_building_etc_line_2 | D343: Street, no., building etc, line 2 | E343: ADDRESS_LINE2_ADDITIONAL_INTERNATIONAL | F343: Street_no_building_etc_line_2
A344: All_addresses.txt (several lines per company) | B344: =LEFT(A344,FIND(".txt",A344)-1) -> All_addresses | C344: =B344&" - "&F344 -> All_addresses - Street_no_building_etc_line_2_native_ | D344: Street, no., building etc, line 2 (native) | E344: ADDRESS_LINE2_ADDITIONAL_LOCAL | F344: Street_no_building_etc_line_2_native_
A345: All_addresses.txt (several lines per company) | B345: =LEFT(A345,FIND(".txt",A345)-1) -> All_addresses | C345: =B345&" - "&F345 -> All_addresses - Street_no_building_etc_line_3 | D345: Street, no., building etc, line 3 | E345: ADDRESS_LINE3_ADDITIONAL_INTERNATIONAL | F345: Street_no_building_etc_line_3
A346: All_addresses.txt (several lines per company) | B346: =LEFT(A346,FIND(".txt",A346)-1) -> All_addresses | C346: =B346&" - "&F346 -> All_addresses - Street_no_building_etc_line_3_native_ | D346: Street, no., building etc, line 3 (native) | E346: ADDRESS_LINE3_ADDITIONAL_LOCAL | F346: Street_no_building_etc_line_3_native_
A347: All_addresses.txt (several lines per company) | B347: =LEFT(A347,FIND(".txt",A347)-1) -> All_addresses | C347: =B347&" - "&F347 -> All_addresses - Street_no_building_etc_line_4 | D347: Street, no., building etc, line 4 | E347: ADDRESS_LINE4_ADDITIONAL_INTERNATIONAL | F347: Street_no_building_etc_line_4
A348: All_addresses.txt (several lines per company) | B348: =LEFT(A348,FIND(".txt",A348)-1) -> All_addresses | C348: =B348&" - "&F348 -> All_addresses - Street_no_building_etc_line_4_native_ | D348: Street, no., building etc, line 4 (native) | E348: ADDRESS_LINE4_ADDITIONAL_LOCAL | F348: Street_no_building_etc_line_4_native_
A349: All_addresses.txt (several lines per company) | B349: =LEFT(A349,FIND(".txt",A349)-1) -> All_addresses | C349: =B349&" - "&F349 -> All_addresses - Postcode | D349: Postcode | E349: POSTCODE_ADDITIONAL | F349: Postcode
A350: All_addresses.txt (several lines per company) | B350: =LEFT(A350,FIND(".txt",A350)-1) -> All_addresses | C350: =B350&" - "&F350 -> All_addresses - City | D350: City | E350: CITY_ADDITIONAL_INTERNATIONAL | F350: City
A351: All_addresses.txt (several lines per company) | B351: =LEFT(A351,FIND(".txt",A351)-1) -> All_addresses | C351: =B351&" - "&F351 -> All_addresses - City_native_ | D351: City (native) | E351: CITY_ADDITIONAL_LOCAL | F351: City_native_
... A483: Detailed_format_industries.txt | B483: =LEFT(A483,FIND(".txt",A483)-1) -> Detailed_format_industries | C483: =B483&" - "&F483 -> Detailed_format_industries - Exchange_rate_from_original_currency | D483: Exchange rate from original currency | E483: EXCHANGE_RATE | F483: Exchange_rate_from_original_currency
A484: Detailed_format_industries.txt | B484: =LEFT(A484,FIND(".txt",A484)-1) -> Detailed_format_industries | C484: =B484&" - "&F484 -> Detailed_format_industries - Total_Current_Assets | D484: Total Current Assets | E484: 13061 | F484: Total_Current_Assets
A485: Detailed_format_industries.txt | B485: =LEFT(A485,FIND(".txt",A485)-1) -> Detailed_format_industries | C485: =B485&" - "&F485 -> Detailed_format_industries - Net_Stated_Inventory | D485: Net Stated Inventory | E485: 20010 | F485: Net_Stated_Inventory
A486: Detailed_format_industries.txt | B486: =LEFT(A486,FIND(".txt",A486)-1) -> Detailed_format_industries | C486: =B486&" - "&F486 -> Detailed_format_industries - Raw_Materials | D486: Raw Materials | E486: 20015 | F486: Raw_Materials
A487: Detailed_format_industries.txt | B487: =LEFT(A487,FIND(".txt",A487)-1) -> Detailed_format_industries | C487: =B487&" - "&F487 -> Detailed_format_industries - Work_in_Progress | D487: Work in Progress | E487: 20020 | F487: Work_in_Progress
A488: Detailed_format_industries.txt | B488: =LEFT(A488,FIND(".txt",A488)-1) -> Detailed_format_industries | C488: =B488&" - "&F488 -> Detailed_format_industries - Finished_Goods | D488: Finished Goods | E488: 20025 | F488: Finished_Goods
A489: Detailed_format_industries.txt | B489: =LEFT(A489,FIND(".txt",A489)-1) -> Detailed_format_industries | C489: =B489&" - "&F489 -> Detailed_format_industries - Inventory_Prepayments | D489: Inventory Prepayments | E489: 20030 | F489: Inventory_Prepayments
A490: Detailed_format_industries.txt | B490: =LEFT(A490,FIND(".txt",A490)-1) -> Detailed_format_industries | C490: =B490&" - "&F490 -> Detailed_format_industries - Net_Accounts_Receivable | D490: Net Accounts Receivable | E490: 13052 | F490: Net_Accounts_Receivable
A491: Detailed_format_industries.txt | B491: =LEFT(A491,FIND(".txt",A491)-1) -> Detailed_format_industries | C491: =B491&" - "&F491 -> Detailed_format_industries - Accounts_Receivable | D491: Accounts Receivable | E491: 20040 | F491: Accounts_Receivable
A492: Detailed_format_industries.txt | B492: =LEFT(A492,FIND(".txt",A492)-1) -> Detailed_format_industries | C492: =B492&" - "&F492 -> Detailed_format_industries - Doubtful_Accounts | D492: Doubtful Accounts | E492: 20045 | F492: Doubtful_Accounts
A493: Detailed_format_industries.txt | B493: =LEFT(A493,FIND(".txt",A493)-1) -> Detailed_format_industries | C493: =B493&" - "&F493 -> Detailed_format_industries - Others_current_assets_ | D493: Others (current assets) | E493: 20050 | F493: Others_current_assets_
A494: Detailed_format_industries.txt | B494: =LEFT(A494,FIND(".txt",A494)-1) -> Detailed_format_industries | C494: =B494&" - "&F494 -> Detailed_format_industries - Other_Current_Assets | D494: Other Current Assets | E494: 20055 | F494: Other_Current_Assets
A495: Detailed_format_industries.txt | B495: =LEFT(A495,FIND(".txt",A495)-1) -> Detailed_format_industries | C495: =B495&" - "&F495 -> Detailed_format_industries - Prepaid_Expenses_Advances | D495: Prepaid Expenses & Advances | E495: 13054 | F495: Prepaid_Expenses_Advances
... A603: Detailed_format_industries.txt | B603: =LEFT(A603,FIND(".txt",A603)-1) -> Detailed_format_industries | C603: =B603&" - "&F603 -> Detailed_format_industries - Dividend_Share_Capital_Other | D603: Dividend Share Capital Other | E603: 13047 | F603: Dividend_Share_Capital_Other
A604: Cash_flow_non_US_industries.txt | B604: =LEFT(A604,FIND(".txt",A604)-1) -> Cash_flow_non_US_industries | C604: =B604&" - "&F604 -> Cash_flow_non_US_industries - BvD_ID_number | D604: BvD ID number | E604: BVD_ID_NUMBER | F604: BvD_ID_number
A605: Cash_flow_non_US_industries.txt | B605: =LEFT(A605,FIND(".txt",A605)-1) -> Cash_flow_non_US_industries | C605: =B605&" - "&F605 -> Cash_flow_non_US_industries - Consolidation_code | D605: Consolidation code | E605: CONSOLIDATION_CODE | F605: Consolidation_code
A606: Cash_flow_non_US_industries.txt | B606: =LEFT(A606,FIND(".txt",A606)-1) -> Cash_flow_non_US_industries | C606: =B606&" - "&F606 -> Cash_flow_non_US_industries - Closing_date | D606: Closing date | E606: CLOSING_DATE | F606: Closing_date
A607: Cash_flow_non_US_industries.txt | B607: =LEFT(A607,FIND(".txt",A607)-1) -> Cash_flow_non_US_industries | C607: =B607&" - "&F607 -> Cash_flow_non_US_industries - Number_of_months | D607: Number of months | E607: NUMBER_MONTHS | F607: Number_of_months
A608: Cash_flow_non_US_industries.txt | B608: =LEFT(A608,FIND(".txt",A608)-1) -> Cash_flow_non_US_industries | C608: =B608&" - "&F608 -> Cash_flow_non_US_industries - Audit_status | D608: Audit status | E608: AUDIT_STATUS | F608: Audit_status
A609: Cash_flow_non_US_industries.txt | B609: =LEFT(A609,FIND(".txt",A609)-1) -> Cash_flow_non_US_industries | C609: =B609&" - "&F609 -> Cash_flow_non_US_industries - Accounting_practice | D609: Accounting practice | E609: ACCOUNTING_PRACTICE | F609: Accounting_practice
A610: Cash_flow_non_US_industries.txt | B610: =LEFT(A610,FIND(".txt",A610)-1) -> Cash_flow_non_US_industries | C610: =B610&" - "&F610 -> Cash_flow_non_US_industries - Source_for_publicly_quoted_companies_ | D610: Source (for publicly quoted companies) | E610: ACCOUNTS_SOURCE_CODE | F610: Source_for_publicly_quoted_companies_
A611: Cash_flow_non_US_industries.txt | B611: =LEFT(A611,FIND(".txt",A611)-1) -> Cash_flow_non_US_industries | C611: =B611&" - "&F611 -> Cash_flow_non_US_industries - Original_units | D611: Original units | E611: ORIGINAL_UNIT | F611: Original_units
A612: Cash_flow_non_US_industries.txt | B612: =LEFT(A612,FIND(".txt",A612)-1) -> Cash_flow_non_US_industries | C612: =B612&" - "&F612 -> Cash_flow_non_US_industries - Original_currency | D612: Original currency | E612: ORIGINAL_CURRENCY | F612: Original_currency
A613: Cash_flow_non_US_industries.txt | B613: =LEFT(A613,FIND(".txt",A613)-1) -> Cash_flow_non_US_industries | C613: =B613&" - "&F613 -> Cash_flow_non_US_industries - Exchange_rate_from_original_currency | D613: Exchange rate from original currency | E613: EXCHANGE_RATE | F613: Exchange_rate_from_original_currency
A614: Cash_flow_non_US_industries.txt | B614: =LEFT(A614,FIND(".txt",A614)-1) -> Cash_flow_non_US_industries | C614: =B614&" - "&F614 -> Cash_flow_non_US_industries - Net_Income_Starting_Line | D614: Net Income / Starting Line | E614: 15500 | F614: Net_Income_Starting_Line
A615: Cash_flow_non_US_industries.txt | B615: =LEFT(A615,FIND(".txt",A615)-1) -> Cash_flow_non_US_industries | C615: =B615&" - "&F615 -> Cash_flow_non_US_industries - Depreciation_Depletion_Amortization | D615: Depreciation, Depletion & Amortization | E615: 15501 | F615: Depreciation_Depletion_Amortization
A616: Cash_flow_non_US_industries.txt | B616: =LEFT(A616,FIND(".txt",A616)-1) -> Cash_flow_non_US_industries | C616: =B616&" - "&F616 -> Cash_flow_non_US_industries - Depreciation_and_Depletion | D616: Depreciation and Depletion | E616: 15502 | F616: Depreciation_and_Depletion
A617: Cash_flow_non_US_industries.txt | B617: =LEFT(A617,FIND(".txt",A617)-1) -> Cash_flow_non_US_industries | C617: =B617&" - "&F617 -> Cash_flow_non_US_industries - Amortization_of_Intangible_Assets | D617: Amortization of Intangible Assets | E617: 15503 | F617: Amortization_of_Intangible_Assets
A618: Cash_flow_non_US_industries.txt | B618: =LEFT(A618,FIND(".txt",A618)-1) -> Cash_flow_non_US_industries | C618: =B618&" - "&F618 -> Cash_flow_non_US_industries - Def_Inc_Taxes_Invest_Tax_Credit | D618: Def. Inc. Taxes & Invest. Tax Credit | E618: 15504 | F618: Def_Inc_Taxes_Invest_Tax_Credit
A619: Cash_flow_non_US_industries.txt | B619: =LEFT(A619,FIND(".txt",A619)-1) -> Cash_flow_non_US_industries | C619: =B619&" - "&F619 -> Cash_flow_non_US_industries - Other_Cash_Flow | D619: Other Cash Flow | E619: 15505 | F619: Other_Cash_Flow
A620: Cash_flow_non_US_industries.txt | B620: =LEFT(A620,FIND(".txt",A620)-1) -> Cash_flow_non_US_industries | C620: =B620&" - "&F620 -> Cash_flow_non_US_industries - Funds_from_Operations_before_WC_Changes_Extra_ | D620: Funds from Operations before WC Changes & Extra. | E620: 15506 | F620: Funds_from_Operations_before_WC_Changes_Extra_
A621: Cash_flow_non_US_industries.txt | B621: =LEFT(A621,FIND(".txt",A621)-1) -> Cash_flow_non_US_industries | C621: =B621&" - "&F621 -> Cash_flow_non_US_industries - Dec_Inc_in_Receivables | D621: Dec/Inc in Receivables | E621: 15508 | F621: Dec_Inc_in_Receivables
A622: Cash_flow_non_US_industries.txt | B622: =LEFT(A622,FIND(".txt",A622)-1) -> Cash_flow_non_US_industries | C622: =B622&" - "&F622 -> Cash_flow_non_US_industries - Dec_Inc_in_Inventories | D622: Dec/Inc in Inventories | E622: 15509 | F622: Dec_Inc_in_Inventories
A623: Cash_flow_non_US_industries.txt | B623: =LEFT(A623,FIND(".txt",A623)-1) -> Cash_flow_non_US_industries | C623: =B623&" - "&F623 -> Cash_flow_non_US_industries - Inc_Dec_in_Accounts_Payable | D623: Inc/Dec in Accounts Payable | E623: 15510 | F623: Inc_Dec_in_Accounts_Payable
A624: Cash_flow_non_US_industries.txt | B624: =LEFT(A624,FIND(".txt",A624)-1) -> Cash_flow_non_US_industries | C624: =B624&" - "&F624 -> Cash_flow_non_US_industries - Inc_Dec_in_Other_Accruals | D624: Inc/Dec in Other Accruals | E624: 15511 | F624: Inc_Dec_in_Other_Accruals
A625: Cash_flow_non_US_industries.txt | B625: =LEFT(A625,FIND(".txt",A625)-1) -> Cash_flow_non_US_industries | C625: =B625&" - "&F625 -> Cash_flow_non_US_industries - Dec_Inc_in_Other_Assets_Liabilities | D625: Dec/Inc in Other Assets/Liabilities | E625: 15512 | F625: Dec_Inc_in_Other_Assets_Liabilities
... A645: Cash_flow_non_US_industries.txt | B645: =LEFT(A645,FIND(".txt",A645)-1) -> Cash_flow_non_US_industries | C645: =B645&" - "&F645 -> Cash_flow_non_US_industries - Cash_Equivalents_at_End_of_Year | D645: Cash & Equivalents at End of Year | E645: 15532 | F645: Cash_Equivalents_at_End_of_Year
A646: Monthly_information.txt | B646: =LEFT(A646,FIND(".txt",A646)-1) -> Monthly_information | C646: =B646&" - "&F646 -> Monthly_information - BvD_ID_number | D646: BvD ID number | E646: BVD_ID_NUMBER | F646: BvD_ID_number
A647: Monthly_information.txt | B647: =LEFT(A647,FIND(".txt",A647)-1) -> Monthly_information | C647: =B647&" - "&F647 -> Monthly_information - ISIN_number | D647: ISIN number | E647: SD_ISIN | F647: ISIN_number
A648: Monthly_information.txt | B648: =LEFT(A648,FIND(".txt",A648)-1) -> Monthly_information | C648: =B648&" - "&F648 -> Monthly_information - Currency | D648: Currency | E648: SD_CURRENCY | F648: Currency
A649: Monthly_information.txt | B649: =LEFT(A649,FIND(".txt",A649)-1) -> Monthly_information | C649: =B649&" - "&F649 -> Monthly_information - Market_price_Year | D649: Market price - Year | F649: Market_price_Year
A650: Monthly_information.txt | B650: =LEFT(A650,FIND(".txt",A650)-1) -> Monthly_information | C650: =B650&" - "&F650 -> Monthly_information - Monthly_Low_price_January | D650: Monthly - Low price - January | E650: MPLOJAN | F650: Monthly_Low_price_January
A651: Monthly_information.txt | B651: =LEFT(A651,FIND(".txt",A651)-1) -> Monthly_information | C651: =B651&" - "&F651 -> Monthly_information - Monthly_Low_price_February | D651: Monthly - Low price - February | E651: MPLOFEB | F651: Monthly_Low_price_February
A652: Monthly_information.txt | B652: =LEFT(A652,FIND(".txt",A652)-1) -> Monthly_information | C652: =B652&" - "&F652 -> Monthly_information - Monthly_Low_price_March | D652: Monthly - Low price - March | E652: MPLOMAR | F652: Monthly_Low_price_March
A653: Monthly_information.txt | B653: =LEFT(A653,FIND(".txt",A653)-1) -> Monthly_information | C653: =B653&" - "&F653 -> Monthly_information - Monthly_Low_price_April | D653: Monthly - Low price - April | E653: MPLOAPR | F653: Monthly_Low_price_April
A654: Monthly_information.txt | B654: =LEFT(A654,FIND(".txt",A654)-1) -> Monthly_information | C654: =B654&" - "&F654 -> Monthly_information - Monthly_Low_price_May | D654: Monthly - Low price - May | E654: MPLOMAY | F654: Monthly_Low_price_May
A655: Monthly_information.txt | B655: =LEFT(A655,FIND(".txt",A655)-1) -> Monthly_information | C655: =B655&" - "&F655 -> Monthly_information - Monthly_Low_price_June | D655: Monthly - Low price - June | E655: MPLOJUN | F655: Monthly_Low_price_June
A656: Monthly_information.txt | B656: =LEFT(A656,FIND(".txt",A656)-1) -> Monthly_information | C656: =B656&" - "&F656 -> Monthly_information - Monthly_Low_price_July | D656: Monthly - Low price - July | E656: MPLOJUL | F656: Monthly_Low_price_July
A657: Monthly_information.txt | B657: =LEFT(A657,FIND(".txt",A657)-1) -> Monthly_information | C657: =B657&" - "&F657 -> Monthly_information - Monthly_Low_price_August | D657: Monthly - Low price - August | E657: MPLOAUG | F657: Monthly_Low_price_August
A658: Monthly_information.txt | B658: =LEFT(A658,FIND(".txt",A658)-1) -> Monthly_information | C658: =B658&" - "&F658 -> Monthly_information - Monthly_Low_price_October | D658: Monthly - Low price - October | E658: MPLOOCT | F658: Monthly_Low_price_October
A659: Monthly_information.txt | B659: =LEFT(A659,FIND(".txt",A659)-1) -> Monthly_information | C659: =B659&" - "&F659 -> Monthly_information - Monthly_Low_price_September | D659: Monthly - Low price - September | E659: MPLOSEP | F659: Monthly_Low_price_September
A660: Monthly_information.txt | B660: =LEFT(A660,FIND(".txt",A660)-1) -> Monthly_information | C660: =B660&" - "&F660 -> Monthly_information - Monthly_Low_price_November | D660: Monthly - Low price - November | E660: MPLONOV | F660: Monthly_Low_price_November
A661: Monthly_information.txt | B661: =LEFT(A661,FIND(".txt",A661)-1) -> Monthly_information | C661: =B661&" - "&F661 -> Monthly_information - Monthly_Low_price_December | D661: Monthly - Low price - December | E661: MPLODEC | F661: Monthly_Low_price_December
... A1061: Banks_Global_financials_and_ratios.txt | B1061: =LEFT(A1061,FIND(".txt",A1061)-1) -> Banks_Global_financials_and_ratios | C1061: =B1061&" - "&F1061 -> Banks_Global_financials_and_ratios - Exchange_rate_from_original_currency | D1061: Exchange rate from original currency | E1061: EXCHANGE_RATE | F1061: Exchange_rate_from_original_currency
A1062: Banks_Global_financials_and_ratios.txt | B1062: =LEFT(A1062,FIND(".txt",A1062)-1) -> Banks_Global_financials_and_ratios | C1062: =B1062&" - "&F1062 -> Banks_Global_financials_and_ratios - Loans | D1062: Loans | E1062: 190000 | F1062: Loans
A1063: Banks_Global_financials_and_ratios.txt | B1063: =LEFT(A1063,FIND(".txt",A1063)-1) -> Banks_Global_financials_and_ratios | C1063: =B1063&" - "&F1063 -> Banks_Global_financials_and_ratios - Gross_loans | D1063: Gross loans | E1063: 190100 | F1063: Gross_loans
A1064: Banks_Global_financials_and_ratios.txt | B1064: =LEFT(A1064,FIND(".txt",A1064)-1) -> Banks_Global_financials_and_ratios | C1064: =B1064&" - "&F1064 -> Banks_Global_financials_and_ratios - Less_reserves_for_impaired_loans_NPLs | D1064: Less: reserves for impaired loans / NPLs | E1064: 190200 | F1064: Less_reserves_for_impaired_loans_NPLs
A1065: Banks_Global_financials_and_ratios.txt | B1065: =LEFT(A1065,FIND(".txt",A1065)-1) -> Banks_Global_financials_and_ratios | C1065: =B1065&" - "&F1065 -> Banks_Global_financials_and_ratios - Other_Earning_Assets | D1065: Other Earning Assets | E1065: 190300 | F1065: Other_Earning_Assets
A1066: Banks_Global_financials_and_ratios.txt | B1066: =LEFT(A1066,FIND(".txt",A1066)-1) -> Banks_Global_financials_and_ratios | C1066: =B1066&" - "&F1066 -> Banks_Global_financials_and_ratios - Loans_and_advances_to_banks | D1066: Loans and advances to banks | E1066: 190400 | F1066: Loans_and_advances_to_banks
A1067: Banks_Global_financials_and_ratios.txt | B1067: =LEFT(A1067,FIND(".txt",A1067)-1) -> Banks_Global_financials_and_ratios | C1067: =B1067&" - "&F1067 -> Banks_Global_financials_and_ratios - Derivatives_Assets_ | D1067: Derivatives (Assets) | E1067: 190500 | F1067: Derivatives_Assets_
A1068: Banks_Global_financials_and_ratios.txt | B1068: =LEFT(A1068,FIND(".txt",A1068)-1) -> Banks_Global_financials_and_ratios | C1068: =B1068&" - "&F1068 -> Banks_Global_financials_and_ratios - Other_securities | D1068: Other securities | E1068: 190600 | F1068: Other_securities
A1069: Banks_Global_financials_and_ratios.txt | B1069: =LEFT(A1069,FIND(".txt",A1069)-1) -> Banks_Global_financials_and_ratios | C1069: =B1069&" - "&F1069 -> Banks_Global_financials_and_ratios - Remaining_earning_assets | D1069: Remaining earning assets | E1069: 190700 | F1069: Remaining_earning_assets
A1070: Banks_Global_financials_and_ratios.txt | B1070: =LEFT(A1070,FIND(".txt",A1070)-1) -> Banks_Global_financials_and_ratios | C1070: =B1070&" - "&F1070 -> Banks_Global_financials_and_ratios - Total_Earning_Assets | D1070: Total Earning Assets | E1070: 190800 | F1070: Total_Earning_Assets
A1071: Banks_Global_financials_and_ratios.txt | B1071: =LEFT(A1071,FIND(".txt",A1071)-1) -> Banks_Global_financials_and_ratios | C1071: =B1071&" - "&F1071 -> Banks_Global_financials_and_ratios - Fixed_Assets | D1071: Fixed Assets | E1071: 190900 | F1071: Fixed_Assets
A1072: Banks_Global_financials_and_ratios.txt | B1072: =LEFT(A1072,FIND(".txt",A1072)-1) -> Banks_Global_financials_and_ratios | C1072: =B1072&" - "&F1072 -> Banks_Global_financials_and_ratios - Non_Earning_Assets | D1072: Non-Earning Assets | E1072: 191000 | F1072: Non_Earning_Assets
A1073: Banks_Global_financials_and_ratios.txt | B1073: =LEFT(A1073,FIND(".txt",A1073)-1) -> Banks_Global_financials_and_ratios | C1073: =B1073&" - "&F1073 -> Banks_Global_financials_and_ratios - Total_assets | D1073: Total assets | E1073: 191100 | F1073: Total_assets
... A1134: Banks_Global_financials_and_ratios.txt | B1134: =LEFT(A1134,FIND(".txt",A1134)-1) -> Banks_Global_financials_and_ratios | C1134: =B1134&" - "&F1134 -> Banks_Global_financials_and_ratios - Tangible_common_equity_Total_business_volume_ | D1134: Tangible common equity/ Total business volume (%) | E1134: 144042 | F1134: Tangible_common_equity_Total_business_volume_
A1135: Banks_Global_financials_and_ratios.txt | B1135: =LEFT(A1135,FIND(".txt",A1135)-1) -> Banks_Global_financials_and_ratios | C1135: =B1135&" - "&F1135 -> Banks_Global_financials_and_ratios - Profit_margin_ | D1135: Profit margin (%) | E1135: PRMA | F1135: Profit_margin_
A1136: Banks_Global_financials_and_ratios.txt | B1136: =LEFT(A1136,FIND(".txt",A1136)-1) -> Banks_Global_financials_and_ratios | C1136: =B1136&" - "&F1136 -> Banks_Global_financials_and_ratios - Net_Interest_Margin_ | D1136: Net Interest Margin (%) | E1136: 195190 | F1136: Net_Interest_Margin_
A1137: Banks_Global_financials_and_ratios.txt | B1137: =LEFT(A1137,FIND(".txt",A1137)-1) -> Banks_Global_financials_and_ratios | C1137: =B1137&" - "&F1137 -> Banks_Global_financials_and_ratios - Net_Int_Rev_Avg_Assets_ | D1137: Net Int. Rev. / Avg Assets (%) | E1137: 195200 | F1137: Net_Int_Rev_Avg_Assets_
A1138: Banks_Global_financials_and_ratios.txt | B1138: =LEFT(A1138,FIND(".txt",A1138)-1) -> Banks_Global_financials_and_ratios | C1138: =B1138&" - "&F1138 -> Banks_Global_financials_and_ratios - Interest_income_on_loans_Average_gross_loans_ | D1138: Interest income on loans/ Average gross loans (%) | E1138: 144043 | F1138: Interest_income_on_loans_Average_gross_loans_
...

Sheet Collibra
A1: Level | B1: File Path | C1: Full Name | D1: Name | E1: Definition | F1: is code for [Business Term] > Name | G1: Technical Data Type | H1: Model ID | I1: Period Criteria | J1: Repetition Criteria | K1: governed by [Data Domain] > Name | L1: Status | M1: Request Code | N1: Supports MDM | O1: Where the field is accessible | P1: is part of [Code Set] > Name
A2: 4 | B2: \\Financial data\Detailed format\Corporate\Profit &amp; loss account | C2: 13000 | D2: 13000 | E2: Amount of total sales unadjusted for the costs related to generating them. It is calculated by adding all sales receipts before discounts, returns and allowances for the period | F2: Gross Sales | G2: MoneyValue | H2: IND | I2: NUMBER_QUARTERS | K2: Company Financials | L2: Active | M2: 313000 | P2: Orbis 4.1 Code Set
A3: 4 | B3: \\Financial data\Accounts header\Key financials &amp; employees\Global standard format\Detailed format\Corporate\Balance sheet\Profit &amp; loss account | C3: 13001 | D3: 13001 | E3: Sum of all the adjustments made to gross sales. It includes discounts, returns, allowances, commission, royalties, excise taxes, etc. | F3: Adjustments / Excise Tax | G3: MoneyValue | H3: IND | I3: NUMBER_YEARS | K3: Company Financials | L3: Active | M3: 313001 | P3: Orbis 4.1 Code Set
A4: 4 | C4: 13002 | D4: 13002 | E4: Amount of gross sales minus adjustments | F4: Net Sales | G4: MoneyValue | H4: IND | K4: Company Financials | L4: Active | M4: 313002 | P4: Orbis 4.1 Code Set
A5: 4 | C5: 13003 | D5: 13003 | E5: Revenue that the company derives from any source other than the sale of goods and services | F5: Other Revenues | G5: MoneyValue | H5: IND | K5: Company Financials | L5: Active | M5: 313003 | P5: Orbis 4.1 Code Set
A6: 4 | C6: 13004 | D6: 13004 | E6: Amount of income generated from the company's sale of goods and services as well as other sources of income from core business functions | F6: Total Revenues | G6: MoneyValue | H6: IND | K6: Company Financials | L6: Active | M6: 313004 | P6: Orbis 4.1 Code Set
A7: 4 | C7: 13018 | D7: 13018 | E7: Earnings before Interest, Tax and Depreciation and Amortization | F7: EBITDA | G7: MoneyValue | H7: IND | K7: Company Financials | L7: Active | M7: 313018 | P7: Orbis 4.1 Code Set
A8: 4 | B8: \\Financial data\Accounts header\Key financials &amp; employees\Global standard format\Detailed format\Corporate\Balance sheet\Profit &amp; loss account | C8: 13019 | D8: 13019 | E8: Portion of a fixed or tangible asset that has been considered consumed during the accounting period | F8: Depreciation | G8: MoneyValue | H8: IND | K8: Company Financials | L8: Active | M8: 313019 | P8: Orbis 4.1 Code Set
A9: 4 | B9: \\Financial data\Detailed format\Corporate\Profit &amp; loss account | C9: 13020 | D9: 13020 | E9: Amortization is the written-off amount of intangible assets over a specified time period. Depletion is the allocated cost of extracting natural resources, such as timber, minerals and oil from the earth | F9: Amortization & Depletion | G9: MoneyValue | H9: IND | I9: NUMBER_YEARS | K9: Company Financials | L9: Active | M9: 313020 | P9: Orbis 4.1 Code Set
A10: 4 | B10: \\Financial data\Detailed format\Corporate\Profit &amp; loss account | C10: 13021 | D10: 13021 | E10: Sum of depreciation, amortization &amp; depletion expenses | F10: Total depreciation, amortization & depletion | G10: MoneyValue | H10: IND | I10: NUMBER_QUARTERS | K10: Company Financials | L10: Active | M10: 313021 | P10: Orbis 4.1 Code Set
A11: 4 | C11: 13022 | D11: 13022 | E11: Amount of income realised from the company's business operations after deducting operating expenses such as cost of goods sold, wages, depreciation and amortization &amp; depletion | G11: MoneyValue | H11: IND | K11: Company Financials | L11: Active | M11: 313022 | P11: Orbis 4.1 Code Set
A12: 4 | B12: \\Financial data\Detailed format\Corporate\Profit &amp; loss account | C12: 13023 | D12: 13023 | E12: Amount of extraordinary pre-tax income and expenses that are infrequent and non-recurring in nature. This includes gains (losses) from disposal of assets, restructuring expenses, merger &amp; acquisition expenses, etc. | F12: Unusual / Exceptional Items | G12: MoneyValue | H12: IND | I12: NUMBER_QUARTERS | K12: Company Financials | L12: Active | M12: 313023 | P12: Orbis 4.1 Code Set
A13: 4 | B13: \\Financial data\Accounts header\Key financials &amp; employees\Global standard format\Detailed format\Banks\Corporate\Balance sheet\Profit &amp; loss account | C13: 13024 | D13: 13024 | E13: All operating revenues minus all operating expenses | F13: Earnings before Interest & Tax | G13: MoneyValue | H13: IND | I13: NUMBER_YEARS | K13: Company Financials | L13: Active | M13: 313024 | P13: Orbis 4.1 Code Set
A14: 4 | B14: \\Financial data\Accounts header\Key financials &amp; employees\Global standard format\Detailed format\Corporate\Balance sheet\Profit &amp; loss account | C14: 13025 | D14: 13025 | E14: Revenue generated from finance activities other than core business functions. It includes interest income, invesment income, income from derivatives, etc. | F14: Financial revenue | G14: MoneyValue | H14: IND | I14: NUMBER_YEARS | K14: Company Financials | L14: Active | M14: 313025 | P14: Orbis 4.1 Code Set
A15: 4 | C15: 13026 | D15: 13026 | E15: Expenditures incurred due to interests, fees and commissions on the company's borrowings from lenders and creditors. This includes expenses from deposit accounts held by the entity, borrowings, subordinated debt and other financial liabilities | G15: MoneyValue | H15: IND | K15: Company Financials | L15: Active | M15: 313026 | P15: Orbis 4.1 Code Set
A16: 4 | B16: \\Financial data\Detailed format\Corporate\Profit &amp; loss account | C16: 13027 | D16: 13027 | E16: Net amount from the income and expenses resulting from the company's financial activities | F16: Financial P/L | G16: MoneyValue | H16: IND | I16: NUMBER_YEARS | K16: Company Financials | L16: Active | M16: 313027 | P16: Orbis 4.1 Code Set
A17: 4 | B17: \\Financial data\Detailed format\Corporate\Profit &amp; loss account | C17: 13034 | D17: 13034 | E17: Company's profit, including all incomes and expenses except income tax expenses | G17: MoneyValue | H17: IND | K17: Company Financials | L17: Active | M17: 313034 | P17: Orbis 4.1 Code Set
A18: 4 | C18: 13035 | D18: 13035 | E18: Amount incurred by the company for the accounting period on its taxable profit | G18: MoneyValue | H18: IND | K18: Company Financials | L18: Active | M18: 313035 | P18: Orbis 4.1 Code Set
A19: 4 | C19: 13037 | D19: 13037 | E19: Company's profit after deducting income tax expense | G19: MoneyValue | H19: IND | K19: Company Financials | L19: Active | M19: 313037 | P19: Orbis 4.1 Code Set
A20: 4 | B20: \\Financial data\Detailed format\Corporate\Profit &amp; loss account | C20: 13038 | D20: 13038 | E20: Share of profit attributable to minority shareholders of the company | F20: Minority Interest | G20: MoneyValue | H20: IND | I20: NUMBER_QUARTERS | K20: Company Financials | L20: Active | M20: 313038 | P20: Orbis 4.1 Code Set
A21: 4 | C21: 13043 | D21: 13043 | E21: Amount of extraordinary after tax income and expenses from events that are unusual and infrequent in nature. It may include pre-acqusition profit, discontinued operations, sale of subsidiaries and joint ventures, etc. | G21: MoneyValue | H21: IND | K21: Company Financials | L21: Active | M21: 313043 | P21: Orbis 4.1 Code Set
A22: 4 | B22: \\Financial data\Accounts header\Key financials &amp; employees\Global standard format\Detailed format\Corporate\Balance sheet\Profit &amp; loss account | C22: 13044 | D22: 13044 | E22: Amount of dividends allocated/distributed to preferred shareholders. It is paid out of net income before dividends on common shares | F22: Preferred Dividends | G22: MoneyValue | H22: IND | I22: NUMBER_QUARTERS | K22: Company Financials | L22: Active | M22: 313044 | P22: Orbis 4.1 Code Set
A23: 4 | C23: 13045 | D23: 13045 | E23: Amount of profit (loss) after tax minus minority interests, other adjustments, extraordinary items after tax and preferred dividends | G23: MoneyValue | H23: IND | K23: Company Financials | L23: Active | M23: 313045 | P23: Orbis 4.1 Code Set
A24: 4 | C24: 13046 | D24: 13046 | E24: Amount of dividends allocated/distributed to common shareholders. It is the portion of earnings paid out to shareholders and not reinvested in the business | F24: Ordinary Dividends | G24: MoneyValue | H24: IND | K24: Company Financials | L24: Active | M24: 313046 | P24: Orbis 4.1 Code Set
A25: 4 | C25: 13047 | D25: 13047 | E25: Dividends to other than ordinary shareholders | F25: Dividend Share Capital Other | G25: MoneyValue | H25: IND | K25: Company Financials | L25: Active | M25: 313047 | P25: Orbis 4.1 Code Set
A26: 5 | B26: \\Financial data\Detailed format\Corporate\Balance sheet\Assets | C26: 13050 | D26: 13050 | E26: Value of company assets that are cash or can be converted into cash immediately. Cash equivalents include bank accounts and other short-term securities with maturities of less than 90 days | F26: Cash or Equivalent | G26: MoneyValue | H26: IND | I26: NUMBER_YEARS | K26: Company Financials | L26: Active | M26: 313050 | P26: Orbis 4.1 Code Set
A27: 5 | B27: \\Financial data\Detailed format\Corporate\Balance sheet\Assets | C27: 13051 | D27: 13051 | E27: Short-term investments also known as marketable securities can easily be converted to cash. It includes any investment instruments that will mature within one year or which are expected to be liquidated within one year. Some common examples may include CDs, money market accounts, treasury bills and government bonds maturing within one year | G27: MoneyValue | H27: IND | K27: Company Financials | L27: Active | M27: 313051 | P27: Orbis 4.1 Code Set
A28: 5 | B28: \\Financial data\Detailed format\Corporate\Balance sheet\Assets | C28: 13052 | D28: 13052 | E28: Gross amount of total money owed to a business by its customers minus allowances for doubtful accounts | F28: Net accounts receivable | G28: MoneyValue | H28: IND | I28: NUMBER_YEARS | K28: Company Financials | L28: Active | M28: 313052 | P28: Orbis 4.1 Code Set
A29: 5 | B29: \\Financial data\Accounts header\Key financials &amp; employees\Global standard format\Detailed format\Banks\Corporate\Balance sheet\Assets | C29: 13054 | D29: 13054 | E29: Amount of expenditures that have not yet been recorded by a company as an expense, but have been paid for in advance. They are initially recorded as assets, because the business will receive goods or services in the future | F29: Prepaid Expenses & Advances | G29: MoneyValue | H29: IND | I29: NUMBER_QUARTERS | K29: Company Financials | L29: Active | M29: 313054 | P29: Orbis 4.1 Code Set
A30: 5 | C30: 13061 | D30: 13061 | E30: Sum of all the assets that are expected to be conveniently sold, consumed, used or exhausted through general business operations within one year of the balance sheet date | G30: MoneyValue | H30: IND | K30: Company Financials | L30: Active | M30: 313061 | P30: Orbis 4.1 Code Set
A31: 5 | B31: \\Financial data\Accounts header\Key financials &amp; employees\Global standard format\Detailed format\Corporate\Balance sheet\Assets | C31: 13068 | D31: 13068 | E31: Value of all buildings, land, furniture, and other physical assets that a business has purchased to run its business. These are net of accumulated depreciation | F31: Net property, plant & equipment | G31: MoneyValue | H31: IND | I31: NUMBER_QUARTERS | K31: Company Financials | L31: Active | M31: 313068 | P31: Orbis 4.1 Code Set
A32: 5 | C32: 13070 | D32: 13070 | E32: Value of an intangible assets that is associated with purchase of one company by another. It is the portion of the purchase price that is higher than the sum of the net fair value of all of the assets purchased in the acquisitions. The value of brand name, customer base, good customer, employee relations and proprietary technology may represent goodwill | F32: Goodwill | G32: MoneyValue | H32: IND | K32: Company Financials | L32: Active | M32: 313070 | P32: Orbis 4.1 Code Set
A33: 5 | C33: 13071 | D33: 13071 | E33: Value of a non-physical assets other than goodwill. These assets may include intellectual property such as patents, trademarks and copyrights | G33: MoneyValue | H33: IND | K33: Company Financials | L33: Active | M33: 313071 | P33: Orbis 4.1 Code Set
A34: 5 | B34: \\Financial data\Accounts header\Key financials &amp; employees\Global standard format\Detailed format\Banks\Corporate\Balance sheet\Assets | C34: 13077 | D34: 13077 | E34: Sum of on-balance sheet assets | F34: Total assets | G34: MoneyValue | H34: IND | I34: NUMBER_YEARS | K34: Company Financials | L34: Active | M34: 313077 | P34: Orbis 4.1 Code Set
A35: 5 | C35: 14004 | D35: 14004 | E35: Portion of long-term debt due within one year | G35: MoneyValue | H35: IND | K35: Company Financials | L35: Active | M35: 314004 | P35: Orbis 4.1 Code Set
A36: 5 | C36: 14011 | D36: 14011 | E36: Sum of all short-term financial obligations due for settlement within one year of the balance sheet date (The sum of Loans, Trade creditors and Total other current liabilities) | G36: MoneyValue | H36: IND | K36: Company Financials | L36: Active | M36: 314011 | P36: Orbis 4.1 Code Set
A37: 5 | B37: \\Financial data\Accounts header\Key financials &amp; employees\Global standard format\Detailed format\Corporate\Balance sheet\Assets\Liabilities | C37: 14014 | D37: 14014 | E37: Payment obligations for leased assets | F37: Lease liabilities | G37: MoneyValue | H37: IND | I37: NUMBER_YEARS | K37: Company Financials | L37: Active | M37: 314014 | P37: Orbis 4.1 Code Set
A38: 5 | B38: \\Financial data\Detailed format\Corporate\Balance sheet\Liabilities | C38: 14016 | D38: 14016 | E38: Sum of all interest-bearing debt maturing in more than one year | F38: Total long-term interest-bearing debt | G38: MoneyValue | H38: IND | I38: NUMBER_QUARTERS | K38: Company Financials | L38: Active | M38: 314016 | P38: Orbis 4.1 Code Set
A39: 5 | C39: 14018 | D39: 14018 | E39: Minority ownership in other entities as part of liabilities | G39: MoneyValue | H39: IND | K39: Company Financials | L39: Active | M39: 314018 | P39: Orbis 4.1 Code Set
A40: 5 | B40: \\Financial data\Detailed format\Corporate\Balance sheet\Liabilities | C40: 14022 | D40: 14022 | E40: Sum of all liabilities | G40: MoneyValue | H40: IND | K40: Company Financials | L40: Active | M40: 314022 | P40: Orbis 4.1 Code Set
A41: 5 | C41: 14025 | D41: 14025 | E41: Perference shares with equity chracteristics and are callable (the issuer as well as investors may have the option to buy back these instruments) | G41: MoneyValue | H41: IND | K41: Company Financials | L41: Active | M41: 314025 | P41: Orbis 4.1 Code Set
A42: 5 | B42: \\Financial data\Detailed format\Corporate\Balance sheet\Liabilities | C42: 14026 | D42: 14026 | E42: Shares ot the company with dividends paid out to shareholders, whose payment takes priority over that of common shares | F42: Preferred Shares | G42: MoneyValue | H42: IND | I42: NUMBER_QUARTERS | K42: Company Financials | L42: Active | M42: 314026 | P42: Orbis 4.1 Code Set
A43: 5 | C43: 14027 | D43: 14027 | E43: Common share capital; holders of such shares are entitled to vote and receive dividends | G43: MoneyValue | H43: IND | K43: Company Financials | L43: Active | M43: 314027 | P43: Orbis 4.1 Code Set
A44: 5 | B44: \\Financial data\Accounts header\Key financials &amp; employees\Global standard format\Detailed format\Banks\Corporate\Balance sheet\Assets\Liabilities | C44: 14029 | D44: 14029 | E44: A special financing tool which secures rights in the issuing company without voting or membership rights | F44: Participation Shares | G44: MoneyValue | H44: IND | I44: NUMBER_YEARS | K44: Company Financials | L44: Active | M44: 314029 | P44: Orbis 4.1 Code Set
A45: 5 | B45: \\Financial data\Accounts header\Key financials &amp; employees\Global standard format\Detailed format\Banks\Corporate\Balance sheet\Assets\Liabilities | C45: 14030 | D45: 14030 | E45: Shares held by the company due to repurchases or buybacks. These shares are issued but no longer outstanding and are not included in the distribution of dividends | F45: Treasury shares | G45: MoneyValue | H45: IND | I45: NUMBER_QUARTERS | K45: Company Financials | L45: Active | M45: 314030 | P45: Orbis 4.1 Code Set
A46: 5 | B46: \\Financial data\Detailed format\Corporate\Balance sheet\Liabilities | C46: 14032 | D46: 14032 | E46: Amount of share premium from the issuance of new shares | F46: Share Premiums | G46: MoneyValue | H46: IND | I46: NUMBER_QUARTERS | K46: Company Financials | L46: Active | M46: 314032 | P46: Orbis 4.1 Code Set
A47: 5 | C47: 14036 | D47: 14036 | E47: <p><span style="color: rgb(11,33,44);white-space: nowrap;background-color: rgb(255,255,255);">Sum of previous periods net income and current period net income</span></p> | G47: MoneyValue | H47: IND | K47: Company Financials | L47: Active | M47: 314036 | P47: Orbis 4.1 Code Set
A48: 5 | C48: 14041 | D48: 14041 | E48: Sum of share capital and other shareholders' funds | G48: MoneyValue | H48: IND | K48: Company Financials | L48: Active | M48: 314041 | P48: Orbis 4.1 Code Set
A49: 5 | C49: 14042 | D49: 14042 | E49: Sum of total liabilities and total shareholders' equity | G49: MoneyValue | H49: IND | K49: Company Financials | L49: Active | M49: 314042 | P49: Orbis 4.1 Code Set
A50: 5 | B50: \\Financial data\Detailed format\Corporate\Balance sheet\Liabilities | C50: 14046 | D50: 14046 | E50: Borrowing in line with arranged limits from lenders due within one year | F50: Current loans & overdrafts | G50: MoneyValue | H50: IND | I50: NUMBER_QUARTERS | K50: Company Financials | L50: Active | M50: 314046 | P50: Orbis 4.1 Code Set
A51: 4 | B51: \\Financial data\Cash flow statement\non-US accounts\Operating cash flows | C51: 15500 | D51: 15500 | E51: Net income amount carried over from the company's income statement | H51: IND_WVB | K51: Company Financials | L51: Active | M51: 315500 | P51: Orbis 4.1 Code Set
A52: 4 | B52: \\Financial data\Accounts header\Key financials &amp; employees\Global standard format\Detailed format\Cash flow statement\US accounts\non-US accounts\Operating cash flows | C52: 15501 | D52: 15501 | E52: Sum of all scheduled non-cash expense (Depreciation, Depletion &amp; Amortization) that is used to reduce the carrying value over the useful life of an asset | F52: Depreciation, Depletion & Amortization | G52: MoneyValue | H52: IND_WVB | I52: NUMBER_YEARS | K52: Company Financials | L52: Active | M52: 315501 | P52: Orbis 4.1 Code Set
A53: 4 | C53: 15502 | D53: 15502 | E53: Depreciation is the non-cash expense to write off the cost of a plant, or machinery over its useful life, giving consideration to wear and tear, obsolescence and salvage value. Depletion is the non-cash expense from the depletion of depletable fixed assets such as oil reserves, forests or mineral extraction rights | G53: MoneyValue | H53: IND_WVB | K53: Company Financials | L53: Active | M53: 315502 | P53: Orbis 4.1 Code Set
A54: 4 | B54: \\Financial data\Cash flow statement\non-US accounts\Operating cash flows | C54: 15503 | D54: 15503 | E54: Non-cash expense due to the written-off amount of intangible assets such as goodwill during the period | F54: Amortization of Intangible Assets | G54: MoneyValue | H54: IND_WVB | I54: NUMBER_QUARTERS | K54: Company Financials | L54: Active | M54: 315503 | P54: Orbis 4.1 Code Set
A55: 4 | C55: 15504 | D55: 15504 | E55: Changes in the deferred income taxes and investment tax credits during the accounting period. An increase has a positive impact on cash flow from operating activities, and vice versa | G55: MoneyValue | H55: IND_WVB | K55: Company Financials | L55: Active | M55: 315504 | P55: Orbis 4.1 Code Set
A56: 4 | C56: 15505 | D56: 15505 | E56: Other non-cash operating cash flow items not specified in the lines above such as provisions, impairment losses etc. | G56: MoneyValue | H56: IND_WVB | K56: Company Financials | L56: Active | M56: 315505 | P56: Orbis 4.1 Code Set
A57: 4 | B57: \\Financial data\Cash flow statement\non-US accounts\Operating cash flows | C57: 15506 | D57: 15506 | E57: Total non-cash operating cash flows before changes in the company's working capital (difference between current assets and current liabilities. It is the amount of money the company has available to pay its short-term expenses) and extraordinary items | G57: MoneyValue | H57: IND_WVB | K57: Company Financials | L57: Active | M57: 315506 | P57: Orbis 4.1 Code Set
A58: 4 | C58: 15507 | D58: 15507 | E58: Other operating cash flow items that cannot be classified as an adjustment item to net income, or an asset/liability as part of changes in non-cash working capital | G58: MoneyValue | H58: IND_WVB | K58: Company Financials | L58: Active | M58: 315507 | P58: Orbis 4.1 Code Set
A59: 4 | C59: 15508 | D59: 15508 | E59: Changes in accounts receivable during the accounting period. An increase in accounts receivable has a negative impact on cash flow from operating activities, and vice versa. | G59: MoneyValue | H59: IND_WVB | K59: Company Financials | L59: Active | M59: 315508 | P59: Orbis 4.1 Code Set
A60: 4 | B60: \\Financial data\Cash flow statement\non-US accounts\Operating cash flows | C60: 15509 | D60: 15509 | E60: Changes in inventories during the accounting period. An increase in inventories has a negative impact on cash flow from operating activities, and vice versa | G60: MoneyValue | H60: IND_WVB | K60: Company Financials | L60: Active | M60: 315509 | P60: Orbis 4.1 Code Set
A61: 4 | C61: 15510 | D61: 15510 | E61: Changes in accounts payable during the accounting period. An increase in accounts payable has a positive impact on cash flow from operating activities, and vice versa | G61: MoneyValue | H61: IND_WVB | K61: Company Financials | L61: Active | M61: 315510 | P61: Orbis 4.1 Code Set
A62: 4 | B62: \\Financial data\Accounts header\Key financials &amp; employees\Global standard format\Detailed format\Cash flow statement\US accounts\non-US accounts\Operating cash flows | C62: 15511 | D62: 15511 | E62: Changes in other accruals during the accounting period. An increase in other accruals has a positive impact on cash flow from operating activities, and vice versa | F62: Inc/Dec in Other Accruals | G62: MoneyValue | H62: IND_WVB | I62: NUMBER_QUARTERS | K62: Company Financials | L62: Active | M62: 315511 | P62: Orbis 4.1 Code Set
A63: 4 | C63: 15512 | D63: 15512 | E63: Changes in other assets/liabilities (from operating activities) during the accounting period not specified in the above lines. If the value of the assets is greater than the value of liabilities, the result has a negative impact on cash flow, and vice versa | G63: MoneyValue | H63: IND_WVB | K63: Company Financials | L63: Active | M63: 315512 | P63: Orbis 4.1 Code Set
A64: 4 | B64: \\Financial data\Accounts header\Key financials &amp; employees\Global standard format\Detailed format\Cash flow statement\US accounts\non-US accounts\Operating cash flows | C64: 15513 | D64: 15513 | E64: Extraordinary items that arised from unusual and infrequent events. These items that were included in net income computation needs to be reversed | F64: Extraordinary Items | G64: MoneyValue | H64: IND_WVB | I64: NUMBER_YEARS | K64: Company Financials | L64: Active | M64: 315513 | P64: Orbis 4.1 Code Set
A65: 4 | B65: \\Financial data\Cash flow statement\non-US accounts\Operating cash flows | C65: 15514 | D65: 15514 | E65: Cash flow generated from the company's ongoing, core business after adjustments to the net income and changes in working capital | F65: Net Cash from Operating Activities | G65: MoneyValue | H65: IND_WVB | I65: NUMBER_QUARTERS | K65: Company Financials | L65: Active | M65: 315514 | P65: Orbis 4.1 Code Set
A66: 4 | B66: \\Financial data\Cash flow statement\non-US accounts\Investing cash flows | C66: 15515 | D66: 15515 | E66: Commonly referred to as capital expenditures. Capital expenditures encompass all expenditures for property, plant and equipment that are necessary to maintain the existing plant and equipment in premium condition, and discretionary expenditures for growth. | F66: Additions to Fixed Assets | G66: MoneyValue | H66: IND_WVB | I66: NUMBER_YEARS | K66: Company Financials | L66: Active | M66: 315515 | P66: Orbis 4.1 Code Set
A67: 4 | B67: \\Financial data\Accounts header\Key financials &amp; employees\Global standard format\Detailed format\Cash flow statement\US accounts\non-US accounts\Operating cash flows\Investing cash flows | C67: 15516 | D67: 15516 | E67: Changes in other long term assets other than capital expenditures and investments. An increase in other long term assets has a negative impact on cash from from investing activities, and vice versa | F67: Increase/Decrease Other Long Term Assets | G67: MoneyValue | H67: IND_WVB | I67: NUMBER_QUARTERS | K67: Company Financials | L67: Active | M67: 315516 | P67: Orbis 4.1 Code Set
A68: 4 | B68: \\Financial data\Cash flow statement\non-US accounts\Investing cash flows | C68: 15517 | D68: 15517 | E68: Changes in investments (e.g. debt and equity instruments of other companies, and acquisitions of other businesses). An increase in investments has a negative impact on cash flow from investing activities, and vice versa | F68: Increase/Decrease in Investments | G68: MoneyValue | H68: IND_WVB | I68: NUMBER_YEARS | K68: Company Financials | L68: Active | M68: 315517 | P68: Orbis 4.1 Code Set
A69: 4 | B69: \\Financial data\Cash flow statement\non-US accounts\Investing cash flows | C69: 15518 | D69: 15518 | E69: Net cash flows from the company's investing activities such as capital expenditures, investments in securities and the sale of securities or assets | F69: Net Cash from Investing Activities | G69: MoneyValue | H69: IND_WVB | I69: NUMBER_QUARTERS | K69: Company Financials | L69: Active | M69: 315518 | P69: Orbis 4.1 Code Set
A70: 4 | B70: \\Financial data\Cash flow statement\non-US accounts\Financing cash flows | C70: 15519 | D70: 15519 | E70: Changes in short term borrowings during the period. An increase in short term borrowings has a positive impact on cash flow from financing activities, and vice versa | F70: Inc/Dec in ST Borrowing | G70: MoneyValue | H70: IND_WVB | I70: NUMBER_YEARS | K70: Company Financials | L70: Active | M70: 315519 | P70: Orbis 4.1 Code Set
A71: 4 | B71: \\Financial data\Accounts header\Key financials &amp; employees\Global standard format\Detailed format\Cash flow statement\US accounts\non-US accounts\Operating cash flows\Investing cash flows\Financing cash flows | C71: 15520 | D71: 15520 | E71: Changes in long term borrowings during the period. An increase in long term borrowings has a positive impact on cash flow from financing activities, and vice versa | F71: Increase/Decrease in Long Term Borrowings | G71: MoneyValue | H71: IND_WVB | I71: NUMBER_QUARTERS | K71: Company Financials | L71: Active | M71: 315520 | P71: Orbis 4.1 Code Set
A72: 4 | C72: 15521 | D72: 15521 | E72: Cash inflow from the sale or issuance of the company's common and preferred stock | G72: MoneyValue | H72: IND_WVB | K72: Company Financials | L72: Active | M72: 315521 | P72: Orbis 4.1 Code Set
A73: 4 | C73: 15522 | D73: 15522 | E73: Changes in shares held by the company due to repurchases or buybacks | F73: Shareholders' Equity Reserve | G73: MoneyValue | H73: IND_WVB | K73: Company Financials | L73: Active | M73: 315522 | P73: Orbis 4.1 Code Set
A74: 4 | C74: 15523 | D74: 15523 | E74: Sum of cash dividends paid to common and preferred shareholders. This amount may be different from the dividends declared in the same period | F74: Cash Dividends Paid - Total | G74: MoneyValue | H74: IND_WVB | K74: Company Financials | L74: Active | M74: 315523 | P74: Orbis 4.1 Code Set
A75: 4 | C75: 15524 | D75: 15524 | E75: Cash dividends paid to common shareholders. This amount may be different from the dividends declared in the same period | F75: Common Dividends (Cash) | G75: MoneyValue | H75: IND_WVB | K75: Company Financials | L75: Active | M75: 315524 | P75: Orbis 4.1 Code Set
A76: 4 | C76: 15525 | D76: 15525 | E76: Cash dividends paid to preferred shareholders. This amount may be different from the dividends declared in the same period | F76: Preferred Dividends (Cash) | G76: MoneyValue | H76: IND_WVB | K76: Company Financials | L76: Active | M76: 315525 | P76: Orbis 4.1 Code Set
A77: 4 | C77: 15526 | D77: 15526 | E77: Cash flows from other financing related activities not specified in the above lines | F77: Other Source/Use - Financing Activities | G77: MoneyValue | H77: IND_WVB | K77: Company Financials | L77: Active | M77: 315526 | P77: Orbis 4.1 Code Set
A78: 4 | C78: 15528 | D78: 15528 | E78: Net flows of cash that are used to fund the company. Financing activities inculde transactions involving debt, equity and dividends. It is calculated by summing up all the cash inflows and outflows related to changes in long-term liabilities and shareholders' equity accounts | G78: MoneyValue | H78: IND_WVB | K78: Company Financials | L78: Active | M78: 315528 | P78: Orbis 4.1 Code Set
A79: 4 | C79: 15529 | D79: 15529 | E79: Changes in cash and cash equivaluent due to translation of foreign currency into the company's functional currency, using exchange rates in effect at the time of the cash flow. | F79: Effect of Exchange Rate on Cash | G79: MoneyValue | H79: IND_WVB | K79: Company Financials | L79: Active | M79: 315529 | P79: Orbis 4.1 Code Set
A80: 4 | B80: \\Financial data\Cash flow statement\non-US accounts\Balance | C80: 15530 | D80: 15530 | E80: Changes in the company's cash and short term investments during the period | F80: Inc/Dec in Cash & ST Investments | G80: MoneyValue | H80: IND_WVB | I80: NUMBER_YEARS | K80: Company Financials | L80: Active | M80: 315530 | P80: Orbis 4.1 Code Set
A81: 4 | B81: \\Financial data\Cash flow statement\non-US accounts\Balance | C81: 15531 | D81: 15531 | E81: Cash &amp; cash equivalents of the company at the beginning of the period. This is the ending balance of cash and cash equivalents of the previous accounting period | G81: MoneyValue | H81: IND_WVB | K81: Company Financials | L81: Active | M81: 315531 | P81: Orbis 4.1 Code Set
A82: 4 | C82: 15532 | D82: 15532 | E82: Cash &amp; cash equivalents of the company at the end of the period. It is the sum of cash flows from operating, investing and financing activities, and the cash &amp; cash equivalents at the beginning of the period | G82: MoneyValue | H82: IND_WVB | K82: Company Financials | L82: Active | M82: 315532 | P82: Orbis 4.1 Code Set
A83: 5 | C83: 20010 | D83: 20010 | E83: Amount of goods and materials after adjustments that a business holds for resale, production or utilization | G83: MoneyValue | H83: IND | K83: Company Financials | L83: Active | M83: 320010 | P83: Orbis 4.1 Code Set
A84: 5 | C84: 20015 | D84: 20015 | E84: Amount of materials or substances used in primary production or manufacturing of goods. These raw materials have not yet been used till date in work in progress or finished goods | G84: MoneyValue | H84: IND | K84: Company Financials | L84: Active | M84: 320015 | P84: Orbis 4.1 Code Set
A85: 5 | C85: 20020 | D85: 20020 | E85: Value of the materials, labor and overhead costs incurred for products that are at various stages of the production process | G85: MoneyValue | H85: IND | K85: Company Financials | L85: Active | M85: 320020 | P85: Orbis 4.1 Code Set
A86: 5 | C86: 20025 | D86: 20025 | E86: Amount of products that have completed the manufacturing process but have not yet been sold or distributed to the customer | G86: MoneyValue | H86: IND | K86: Company Financials | L86: Active | M86: 320025 | P86: Orbis 4.1 Code Set
A87: 5 | C87: 20030 | D87: 20030 | E87: Inventory prepayment is the amount of inventory for which the business have paid but have not yet received. This line also includes any other adjustments related to inventory | G87: MoneyValue | H87: IND | K87: Company Financials | L87: Active | M87: 320030 | P87: Orbis 4.1 Code Set
A88: 5 | C88: 20040 | D88: 20040 | E88: Gross amount of money due to a business for goods or services delivered or used but not yet paid for by its customers. It is the amount of money owed by customers for purchases made on credit | G88: MoneyValue | H88: IND | K88: Company Financials | L88: Active | M88: 320040 | P88: Orbis 4.1 Code Set
A89: 5 | B89: \\Financial data\Detailed format\Corporate\Balance sheet\Assets | C89: 20045 | D89: 20045 | E89: Amount of allowances made against a portion of accounts receivable that is expected to be uncollectible | F89: Doubtful accounts & allowances | G89: MoneyValue | H89: IND | I89: NUMBER_QUARTERS | K89: Company Financials | L89: Active | M89: 320045 | P89: Orbis 4.1 Code Set
A90: 5 | C90: 20050 | D90: 20050 | E90: Sum of all the other current assets not specified in other lines. It includes prepared expenses &amp; advances, deferred charges and other current assets | G90: MoneyValue | H90: IND | K90: Company Financials | L90: Active | M90: 320050 | P90: Orbis 4.1 Code Set
A91: 5 | B91: \\Financial data\Detailed format\Corporate\Balance sheet\Assets | C91: 20055 | D91: 20055 | E91: Amount of other current assets not specified in other lines. These assets can be converted into cash within one business cycle in less than one year | F91: Other current assets | G91: MoneyValue | H91: IND | I91: NUMBER_QUARTERS | K91: Company Financials | L91: Active | M91: 320055 | P91: Orbis 4.1 Code Set
A92: 5 | C92: 20065 | D92: 20065 | E92: Expenditure that is paid for in current accounting period, but for which the underlying assets will not be entirely consumed until one or more future periods. It is carried on the balance sheet as an asset until it is fully consumed | G92: MoneyValue | H92: IND | K92: Company Financials | L92: Active | M92: 320065 | P92: Orbis 4.1 Code Set
A93: 5 | B93: \\Financial data\Detailed format\Corporate\Balance sheet\Assets | C93: 20070 | D93: 20070 | E93: Sum of cash &amp; cash equivalents and short-term investments | F93: Total Cash & Short Term Investment | G93: MoneyValue | H93: IND | I93: NUMBER_YEARS | K93: Company Financials | L93: Active | M93: 320070 | P93: Orbis 4.1 Code Set
A94: 5 | B94: \\Financial data\Detailed format\Corporate\Balance sheet\Assets | C94: 20085 | D94: 20085 | E94: Sum of all the long-term assets for which the full value will not be realized within the accounting year. It includes long-term investments, fixed assets and intangible assets | G94: MoneyValue | H94: IND | K94: Company Financials | L94: Active | M94: 320085 | P94: Orbis 4.1 Code Set
A95: 5 | B95: \\Financial data\Accounts header\Key financials &amp; employees\Global standard format\Detailed format\Banks\Corporate\Balance sheet\Assets | C95: 20095 | D95: 20095 | E95: Gross balance sheet value of the long-term real estate that is exclusive of any buildings or other fixed assets situated on it | F95: Land | G95: MoneyValue | H95: IND | K95: Company Financials | L95: Active | M95: 320095 | P95: Orbis 4.1 Code Set
A96: 5 | B96: \\Financial data\Accounts header\Key financials &amp; employees\Global standard format\Detailed format\Banks\Corporate\Balance sheet\Assets | C96: 20100 | D96: 20100 | E96: Amount of accumulated depreciation on land | F96: Accumulated depreciation on land | G96: MoneyValue | H96: IND | I96: NUMBER_YEARS | K96: Company Financials | L96: Active | M96: 320100 | P96: Orbis 4.1 Code Set
A97: 5 | C97: 20105 | D97: 20105 | E97: Gross value of land minus the amount of accumulated depreciation | G97: MoneyValue | H97: IND | K97: Company Financials | L97: Active | M97: 320105 | P97: Orbis 4.1 Code Set
A98: 5 | C98: 20110 | D98: 20110 | E98: Gross balance sheet value of long-term assets which shows the cost of buildings | F98: Buildings | G98: MoneyValue | H98: IND | K98: Company Financials | L98: Active | M98: 320110 | P98: Orbis 4.1 Code Set
A99: 5 | B99: \\Financial data\Accounts header\Key financials &amp; employees\Global standard format\Detailed format\Corporate\Balance sheet\Assets | C99: 20115 | D99: 20115 | E99: Amount of cumulative depreciation on buildings up to the balance sheet date | F99: Total Buildings Depreciation | G99: MoneyValue | H99: IND | I99: NUMBER_QUARTERS | K99: Company Financials | L99: Active | M99: 320115 | P99: Orbis 4.1 Code Set
A100: 5 | B100: \\Financial data\Accounts header\Key financials &amp; employees\Global standard format\Detailed format\Corporate\Balance sheet\Assets | C100: 20120 | D100: 20120 | E100: Gross value of buildings minus accumulated deprecation | F100: Net buildings | G100: MoneyValue | H100: IND | I100: NUMBER_QUARTERS | K100: Company Financials | L100: Active | M100: 320120 | P100: Orbis 4.1 Code Set
...
